Workbook
Name ___________________________________________________________sp: 6
Name ___________________________________________________________sp_1: 6
Name __________________________________________________________sp: 6
Name __________________________________________________________sp_1: 6
Name _________________________________________________________sp: 6
Name _________________________________________________________sp_1: 6
Name ________________________________________________________sp: 6
Name ________________________________________________________sp_1: 6
Name _______________________________________________________sp: 6
Name _______________________________________________________sp_1: 6
Name ______________________________________________________sp: 6
Name ______________________________________________________sp_1: 6
Name _____________________________________________________sp: 6
Name _____________________________________________________sp_1: 6
Name ____________________________________________________sp: 6
Name ____________________________________________________sp_1: 6
Name ___________________________________________________sp: 6
Name ___________________________________________________sp_1: 6
Name __________________________________________________sp: 6
Name __________________________________________________sp_1: 6
Name _________________________________________________sp: 6
Name _________________________________________________sp_1: 6
Name ________________________________________________sp: 6
Name ________________________________________________sp_1: 6
Name _______________________________________________sp: 6
Name _______________________________________________sp_1: 6
Name ______________________________________________sp: 6
Name ______________________________________________sp_1: 6
Name _____________________________________________sp: 6
Name _____________________________________________sp_1: 6
Name ____________________________________________sp: 6
Name ____________________________________________sp_1: 6
Name ___________________________________________sp: 6
Name ___________________________________________sp_1: 6
Name __________________________________________sp: 6
Name __________________________________________sp_1: 6
Name _________________________________________sp: 6
Name _________________________________________sp_1: 6
Name ________________________________________sp: 6
Name ________________________________________sp_1: 6
Name _______________________________________sp: 6
Name _______________________________________sp_1: 6
Name ______________________________________sp: 6
Name ______________________________________sp_1: 6
Name _____________________________________sp: 6
Name _____________________________________sp_1: 6
Name ____________________________________sp: 6
Name ____________________________________sp_1: 6
Name ___________________________________sp: 6
Name ___________________________________sp_1: 6
Name __________________________________sp: 6
Name __________________________________sp_1: 6
Name _________________________________sp: 6
Name _________________________________sp_1: 6
Name ________________________________sp: 6
Name ________________________________sp_1: 6
Name _______________________________sp: 6
Name _______________________________sp_1: 6
Name ______________________________sp: 6
Name ______________________________sp_1: 6

Sheet 主要财务指标（报表数）
A1: 主要财务指标表
A3: 类别 | B3: 指标名称 | C3: 2017年 | D3: 2018年 | E3: 2019年 | F3: 2020年 | G3: 2021年 | H3: 2022年 | I3: 2021年（分月） | U3: 2022年（分月） | AG3: 2023年（分月） | AT3: 辅助计算列 | AU3: 辅助计算列
I4: 1月 | J4: 2月 | K4: 3月 | L4: 4月 | M4: 5月 | N4: 6月 | O4: 7月 | P4: 8月 | Q4: 9月 | R4: 10月 | S4: 11月 | T4: 12月 | U4: 1月 | V4: 2月 | W4: 3月 | X4: 4月 | Y4: 5月 | Z4: 6月 | AA4: 7月 | AB4: 8月 | AC4: 9月 | AD4: 10月 | AE4: 11月 | AF4: 12月 | AG4: 1月 | AH4: 2月 | AI4: 3月 | AJ4: 4月 | AK4: 5月 | AL4: 6月 | AM4: 7月 | AN4: 8月 | AO4: 9月 | AP4: 10月 | AQ4: 11月 | AR4: 12月 | AS4: 2023年累计 | AT4: 当月 | AU4: 本年累计
A5: 两利五率 | B5: 利润总额（万元） | C5: 6711.61 | D5: 10560.68 | E5: 11207 | F5: -28039.37 | G5: 130688.46 | H5: 117467.79 | I5: 128.1 | J5: 1559.79 | K5: 6904.08 | L5: 12680.2 | M5: 15888.91 | N5: 17126.56 | O5: 14267.67 | P5: 12929.48 | Q5: 17664.28 | R5: 23599.75 | S5: 18347.83 | T5: -10408.2 | U5: 871.13 | V5: 6044.58 | W5: 18821.08 | X5: 26499.07 | Y5: 14703.68 | Z5: 19573.63 | AA5: 21835.91 | AB5: 10885.34 | AC5: 6507.94 | AD5: 2495.53 | AE5: 247.79 | AF5: -11017.89 | AG5: =[5]基础财务数据!AN46 -> -7512.17 | AH5: =[5]基础财务数据!AO46 -> 1344.27 | AI5: =[5]基础财务数据!AP46 -> 814.02 | AJ5: =[5]基础财务数据!AQ46 -> 269.6 | AK5: =[5]基础财务数据!AR46 -> -8845.92 | AL5: =[5]基础财务数据!AS46 -> -9496.48 | AM5: =[5]基础财务数据!AT46 -> 0 | AN5: =[5]基础财务数据!AU46 -> 0 | ... AS5: =[5]基础财务数据!AZ46 -> -23426.67
B6: 净利润（万元） | C6: 26492.38 | D6: 13342.04 | E6: 2799.01 | F6: -29465.96 | G6: 112874.56 | H6: 101993 | I6: 128.1 | J6: 1559.79 | K6: 6901.43 | L6: 12680.2 | M6: 15888.91 | N6: 17126.56 | O6: 3111 | P6: 12929.48 | Q6: 17664.28 | R6: 23599.91 | S6: 18347.83 | T6: -17062.93 | U6: 870.95 | V6: 6044.58 | W6: 16025.14 | X6: 22757.93 | Y6: 14234.88 | Z6: 16921.5 | AA6: 18793.01 | AB6: 9398.96 | AC6: 5621.17 | AD6: 2197.38 | AE6: 247.79 | AF6: -11120.29 | AG6: =[5]基础财务数据!AN48 -> -7512.17 | AH6: =[5]基础财务数据!AO48 -> 1344.27 | AI6: =[5]基础财务数据!AP48 -> 805.9 | AJ6: =[5]基础财务数据!AQ48 -> 269.6 | AK6: =[5]基础财务数据!AR48 -> -8369.64 | AL6: =[5]基础财务数据!AS48 -> -9494.68 | AM6: =[5]基础财务数据!AT48 -> 0 | AN6: =[5]基础财务数据!AU48 -> 0 | ... AS6: =[5]基础财务数据!AZ48 -> -22956.72
B7: 资产负债率（%） | C7: 87.37 | D7: 51.8 | E7: 51.67 | F7: 55.91 | G7: 39.18 | H7: 24.36 | I7: 54.58 | J7: 54.81 | K7: 53 | L7: 53.31 | M7: 51.95 | N7: 48.98 | O7: 48.61 | P7: 46.39 | Q7: 43.71 | R7: 41.89 | S7: 41.41 | T7: 39.18 | U7: 38.85 | V7: 38.56 | W7: 37.49 | X7: 34.38 | Y7: 33.02 | Z7: 27.74 | AA7: 26.59 | AB7: 24.84 | AC7: 25.42 | AD7: 25.86 | AE7: 27.22 | AF7: 24.36 | AG7: =[5]基础财务数据!AN10/[5]基础财务数据!AN5*100 -> 24.492639 | AH7: =[5]基础财务数据!AO10/[5]基础财务数据!AO5*100 -> 24.262651 | AI7: =[5]基础财务数据!AP10/[5]基础财务数据!AP5*100 -> 23.49834 | AJ7: =[5]基础财务数据!AQ10/[5]基础财务数据!AQ5*100 -> 32.537887 | AK7: =[5]基础财务数据!AR10/[5]基础财务数据!AR5*100 -> 34.667123 | AL7: =[5]基础财务数据!AS10/[5]基础财务数据!AS5*100 -> 34.315029 | AM7: =[5]基础财务数据!AT10/[5]基础财务数据!AT5*100 -> #DIV/0! | AN7: =[5]基础财务数据!AU10/[5]基础财务数据!AU5*100 -> #DIV/0! | ... AR7: =[5]基础财务数据!AY10/[5]基础财务数据!AY5*100 -> #DIV/0! | AS7: 34.32 | AU7: ='[5]主要分析指标表（底稿）'!G14 -> 34.32
B8: 净资产收益率(%) | C8: 30.75 | D8: 6.93 | E8: 0.98 | F8: -10.47 | G8: 34.52 | H8: 24.53 | I8: 0.05 | J8: 0.56 | K8: 2.45 | L8: 4.38 | M8: 5.28 | N8: 5.4 | O8: 0.95 | P8: 3.89 | Q8: 5.08 | R8: 6.44 | S8: 4.75 | T8: -4.42 | U8: 0.23 | V8: 1.59 | W8: 4.12 | X8: 5.75 | Y8: 3.53 | Z8: 4.11 | AA8: 4.49 | AB8: 2.22 | AC8: 1.32 | AD8: 0.52 | AE8: 0.06 | AF8: -2.67 | AG8: =[5]基础财务数据!AN48/([5]基础财务数据!AL16+[5]基础财务数据!AN16)*2*100 -> -1.6665728 | AH8: =[5]基础财务数据!AO48/([5]基础财务数据!AN16+[5]基础财务数据!AO16)*2*100 -> 0.3002452 | AI8: =[5]基础财务数据!AP48/([5]基础财务数据!AO16+[5]基础财务数据!AP16)*2*100 -> 0.17953215 | AJ8: =[5]基础财务数据!AQ48/([5]基础财务数据!AP16+[5]基础财务数据!AQ16)*2*100 -> 0.064344743 | AK8: =[5]基础财务数据!AR48/([5]基础财务数据!AQ16+[5]基础财务数据!AR16)*2*100 -> -2.1768449 | AL8: =[5]基础财务数据!AS48/([5]基础财务数据!AR16+[5]基础财务数据!AS16)*2*100 -> -2.5277719 | AM8: =[5]基础财务数据!AT48/([5]基础财务数据!AS16+[5]基础财务数据!AT16)*2*100 -> 0 | AN8: =[5]基础财务数据!AU48/([5]基础财务数据!AT16+[5]基础财务数据!AU16)*2*100 -> #DIV/0! | AO8: =[5]基础财务数据!AV48/([5]基础财务数据!AU16+[5]基础财务数据!AV16)*2*100 -> #DIV/0! | ... AR8: =[5]基础财务数据!AY48/([5]基础财务数据!AX16+[5]基础财务数据!AY16)*2*100 -> #DIV/0! | AS8: -11.13 | AU8: ='[5]主要分析指标表（底稿）'!C29 -> -11.13
B9: 营业现金比率（%） | C9: 8.79 | D9: 10.96 | E9: 7.44 | F9: 1.28 | G9: 17.1 | H9: 12.39 | I9: =[5]基础财务数据!O50/[5]基础财务数据!O20*100 -> -40.048534 | J9: =[5]基础财务数据!P50/[5]基础财务数据!P20*100 -> 13.776103 | K9: =[5]基础财务数据!Q50/[5]基础财务数据!Q20*100 -> -8.04813 | L9: =[5]基础财务数据!R50/[5]基础财务数据!R20*100 -> 29.239416 | M9: =[5]基础财务数据!S50/[5]基础财务数据!S20*100 -> 28.844554 | N9: =[5]基础财务数据!T50/[5]基础财务数据!T20*100 -> 24.797923 | O9: =[5]基础财务数据!U50/[5]基础财务数据!U20*100 -> 46.856099 | P9: =[5]基础财务数据!V50/[5]基础财务数据!V20*100 -> 11.855634 | ... T9: =[5]基础财务数据!Z50/[5]基础财务数据!Z20*100 -> -197.55104 | U9: 12.36 | V9: 19.41 | W9: 36.29 | X9: 27.66 | Y9: 15.89 | Z9: 32.44 | AA9: 10.4 | AB9: 0.96 | AC9: 15.1 | AD9: 2.55 | AE9: 6.89 | AF9: -31.32 | AG9: =[5]基础财务数据!AN50/[5]基础财务数据!AN20*100 -> -14.964807 | AH9: =[5]基础财务数据!AO50/[5]基础财务数据!AO20*100 -> 4.2446855 | AI9: =[5]基础财务数据!AP50/[5]基础财务数据!AP20*100 -> 0.14908914 | AJ9: =[5]基础财务数据!AQ50/[5]基础财务数据!AQ20*100 -> 6.815033 | AK9: =[5]基础财务数据!AR50/[5]基础财务数据!AR20*100 -> 8.0407451 | AL9: =[5]基础财务数据!AS50/[5]基础财务数据!AS20*100 -> -48.547044 | AM9: =[5]基础财务数据!AT50/[5]基础财务数据!AT20*100 -> #DIV/0! | AN9: =[5]基础财务数据!AU50/[5]基础财务数据!AU20*100 -> #DIV/0! | ... AR9: =[5]基础财务数据!AY50/[5]基础财务数据!AY20*100 -> #DIV/0! | AS9: 1.4 | AU9: ='[5]主要分析指标表（底稿）'!C37 -> 1.4
B10: 全员劳动生产率（万元/人） | C10: 42.4 | D10: 50.24 | E10: 48.9 | F10: 33.91 | G10: 114.16 | H10: -1.9 | I10: 3.87 | J10: 4.71 | K10: 7.65 | L10: 12.57 | M10: 16.69 | N10: 12.21 | O10: 11.73 | P10: 11.32 | Q10: 10.45 | R10: 14.2 | S10: 6.45 | T10: -2.83 | U10: 5.66 | V10: 8.66 | W10: 14.07 | X10: 16.87 | Y10: 11.84 | Z10: 13.95 | AA10: 15.29 | AB10: 10.05 | AC10: 8 | AD10: 4.45 | AE10: 3.24 | AF10: -1.84 | AG10: 2.39 | AH10: =[5]全员劳动生产率!AH5 -> 2.89 | AI10: =[5]全员劳动生产率!AI5 -> 3.78 | AJ10: =[5]全员劳动生产率!AJ5 -> 5.47 | AK10: =[5]全员劳动生产率!AK5 -> 0.95 | AL10: =[5]全员劳动生产率!AL5 -> 0.65 | AM10: =[5]全员劳动生产率!AM5 -> 0 | AN10: =[5]全员劳动生产率!AN5 -> 0 | AO10: =[5]全员劳动生产率!AO5 -> 0 | ... AR10: =[5]全员劳动生产率!AR5 -> 0 | AS10: 30.32 | AU10: ='[5]主要分析指标表（底稿）'!G30/10000 -> 30.323313
B11: 研发投入强度（%） | C11: 0.69 | D11: 0.56 | E11: 0.53 | F11: 0.73 | G11: 0.76 | H11: 0.78 | I11: 0.69 | J11: 0.32 | K11: 0.98 | L11: 0.75 | M11: 0.79 | N11: 0.2 | O11: 0.22 | P11: 0.35 | Q11: 0.29 | R11: 0.41 | S11: 0.87 | T11: 7.57 | U11: 0.45 | V11: 0.49 | W11: 0.31 | X11: 0.32 | Y11: 0.78 | Z11: 0.24 | AA11: 0.66 | AB11: 0.72 | AC11: 0.73 | AD11: 1.21 | AE11: 1.65 | AF11: 2.47 | AG11: 0.45 | AH11: 0.66 | AI11: 0.83 | AJ11: 0.78 | AK11: 0.92 | AL11: 1.82 | AS11: 0.9 | AU11: ='[5]主要分析指标表（底稿）'!G31 -> 0.9
A12: 成本控制 | B12: 万元产值综合能耗（吨标煤/万元） | C12: 2.84 | D12: 3.02 | E12: 2.85 | F12: 3.5 | G12: 3.35 | H12: 3.34 | I12: 3.53 | J12: 3.44 | K12: 3.6 | L12: 3.42 | M12: 3.34 | N12: 3.27 | O12: 3.45 | P12: 3.36 | Q12: 3.33 | R12: 3.19 | S12: 3.28 | T12: 2.87 | U12: 4.39 | V12: 3.2 | W12: 3.15 | X12: 3.27 | Y12: 4.09 | Z12: 3.44 | AA12: 3.26 | AB12: 3.31 | AC12: 3.2 | AD12: 3.15 | AE12: 3.16 | AF12: 3.13 | AG12: 5.09 | AH12: 4.01 | AI12: 4.05 | AJ12: 4.01 | AK12: 3.83 | AL12: 3.79 | AS12: 4.08 | AW12: 只有统计指标解释，甲醇作为能源产品抵扣只是总公司内部执行的，由于从今年起国家改变了综合能源考核办法，用天然气、煤作为原料生产化工产品的企业，原料天然气、煤在能源消费考核中将不视为能源消费，既然天然气原料部分不视为能源消费了，那么用其生产的甲醇也就不能在视做能源产品进行抵扣，因而年报会上总部决定取消在总公司内将甲醇、乙烯视为能源拼抵扣的计算方法
B13: 维修费占固定资产原值比例(%) | C13: 2.1 | D13: 3.12 | E13: 2.26 | F13: 2.46 | G13: 4.6 | H13: 3.55 | I13: 0.21 | J13: 0.11 | K13: 0.26 | L13: 0.47 | M13: 0.18 | N13: 0.07 | O13: 0.07 | P13: 0.25 | Q13: 0.22 | R13: 0.29 | S13: 0.91 | T13: -1.22 | U13: 0.2 | V13: 0.53 | W13: 0 | X13: 0.03 | Y13: 0.08 | Z13: 0.11 | AA13: 0.11 | AB13: 0.12 | AC13: 0.2 | AD13: 0.67 | AE13: 1.02 | AF13: 0.47 | AG13: ='[5]资产负债、利润（底稿）'!J78/'[5]资产负债、利润（底稿）'!L33*100 -> 0.66479076 | AH13: 0.1 | AI13: 0.16 | AJ13: 0.17 | AK13: 0.19 | AL13: 0.24 | AS13: 0.9 | AT13: ='[5]资产负债、利润（底稿）'!K78/'[5]资产负债、利润（底稿）'!C33*100 -> 0.23766646 | AU13: ='[5]资产负债、利润（底稿）'!I78/'[5]资产负债、利润（底稿）'!C33*100 -> 0.89961913
A14: 偿债能力 | B14: 现金流动负债比率(%) | C14: 10.06 | D14: 22.22 | E14: 14.97 | F14: 2.01 | G14: 60.76 | H14: 82.38 | I14: -5.2 | J14: 2 | K14: -1.52 | L14: 6.93 | M14: 6.99 | N14: 6.1 | O14: 11.52 | P14: 3.42 | Q14: 8.43 | R14: 11.62 | S14: 12.87 | T14: -17.39 | U14: 2.18 | V14: 6.44 | W14: 15.69 | X14: 12.12 | Y14: 5.34 | Z14: 16.89 | AA14: 5.89 | AB14: 0.49 | AC14: 7 | AD14: 1.07 | AE14: 2.84 | AF14: -14.56 | AG14: =[5]基础财务数据!AN50/[5]基础财务数据!AN57*100 -> -5.3282608 | AH14: =[5]基础财务数据!AO50/[5]基础财务数据!AO57*100 -> 2.0161811 | AI14: =[5]基础财务数据!AP50/[5]基础财务数据!AP57*100 -> 0.085043601 | AJ14: =[5]基础财务数据!AQ50/[5]基础财务数据!AQ57*100 -> 2.7941446 | AK14: =[5]基础财务数据!AR50/[5]基础财务数据!AR57*100 -> 2.4765979 | AL14: =[5]基础财务数据!AS50/[5]基础财务数据!AS57*100 -> -12.364468 | AM14: =[5]基础财务数据!AT50/[5]基础财务数据!AT57*100 -> #DIV/0! | AN14: =[5]基础财务数据!AU50/[5]基础财务数据!AU57*100 -> #DIV/0! | ... AR14: =[5]基础财务数据!AY50/[5]基础财务数据!AY57*100 -> #DIV/0! | AS14: 5.53 | AU14: ='[5]主要分析指标表（底稿）'!G18 -> 5.53
B15: 速动比率 | C15: 0.02 | D15: 0.06 | E15: 0.09 | F15: 0.13 | G15: 0.07 | H15: 0.32 | I15: 0.1 | J15: 0.1 | K15: 0.1 | L15: 0.13 | M15: 0.16 | N15: 0.13 | O15: 0.15 | P15: 15.58 | Q15: 16.63 | R15: 20.72 | S15: 29.17 | T15: 7.25 | U15: 0.1 | V15: 0.13 | W15: 0.2 | X15: 0.19 | Y15: 0.23 | Z15: 0.4 | AA15: 0.45 | AB15: 0.47 | AC15: 0.54 | AD15: 0.46 | AE15: 0.48 | AF15: 0.32 | AG15: =([5]基础财务数据!AN58-[5]基础财务数据!AN9)/[5]基础财务数据!AN57 -> 0.25154105 | AH15: =([5]基础财务数据!AO58-[5]基础财务数据!AO9)/[5]基础财务数据!AO57 -> 0.25067815 | AI15: =([5]基础财务数据!AP58-[5]基础财务数据!AP9)/[5]基础财务数据!AP57 -> 0.2481386 | AJ15: =([5]基础财务数据!AQ58-[5]基础财务数据!AQ9)/[5]基础财务数据!AQ57 -> 0.14065759 | AK15: =([5]基础财务数据!AR58-[5]基础财务数据!AR9)/[5]基础财务数据!AR57 -> 0.1321764 | AL15: =([5]基础财务数据!AS58-[5]基础财务数据!AS9)/[5]基础财务数据!AS57 -> 0.099049595 | AM15: =([5]基础财务数据!AT58-[5]基础财务数据!AT9)/[5]基础财务数据!AT57 -> #DIV/0! | AN15: =([5]基础财务数据!AU58-[5]基础财务数据!AU9)/[5]基础财务数据!AU57 -> #DIV/0! | ... AR15: =([5]基础财务数据!AY58-[5]基础财务数据!AY9)/[5]基础财务数据!AY57 -> #DIV/0! | AS15: 0.1 | AT15: =('[5]资产负债、利润（底稿）'!C22-'[5]资产负债、利润（底稿）'!C17)/'[5]资产负债、利润（底稿）'!G23 -> 0.099049594 | AU15: =AT15 -> 0.099049594
A16: 运营能力 | B16: 总资产周转率(次) | C16: 0.84 | D16: 0.91 | E16: 0.92 | F16: 0.78 | G16: 1.26 | H16: 1.51 | I16: 0.06 | J16: 0.07 | K16: 0.09 | L16: 0.12 | M16: 0.12 | N16: 0.11 | O16: 0.11 | P16: 0.12 | Q16: 0.12 | R16: 0.14 | S16: 0.12 | T16: 0.04 | U16: 0.1 | V16: 0.12 | W16: 0.15 | X16: 0.14 | Y16: 0.11 | Z16: 0.13 | AA16: 0.14 | AB16: 0.11 | AC16: 0.11 | AD16: 0.1 | AE16: 0.1 | AF16: 0.09 | AG16: 0.1 | AH16: 0.11 | AI16: 0.11 | AJ16: 0.11 | AK16: 0.11 | AL16: 0.11 | AS16: 1.26 | AT16: =[5]基础财务数据!AO20/([5]基础财务数据!AN5+[5]基础财务数据!AO5)*2 -> 0.10867676 | AU16: ='[5]主要分析指标表（底稿）'!G6 -> 1.26
B17: 应收账款周转率(次) | C17: 58.84 | D17: 148 | E17: 95.93 | F17: 70.96 | G17: 202.69 | H17: 179.58 | I17: 4.46 | J17: 3.47 | K17: 3.25 | L17: 3.93 | M17: 4.54 | N17: 5.15 | O17: 7.3 | P17: 7.97 | Q17: 6.56 | R17: 5.28 | S17: 5.17 | T17: 4.99 | U17: 14.37 | V17: 10.45 | W17: 10.83 | X17: 11.64 | Y17: 10.02 | Z17: 13.26 | AA17: 12.25 | AB17: 11.51 | AC17: 9.55 | AD17: 11.38 | AE17: 9.85 | AF17: 12.56 | AG17: 181.19 | AH17: 5.04 | AI17: 5.04 | AJ17: 5.04 | AK17: 5.04 | AL17: 5.04 | AS17: 91.69 | AT17: =[5]基础财务数据!AO21/([5]基础财务数据!AO7+[5]基础财务数据!AN7)*2 -> 5.0368481 | AU17: ='[5]主要分析指标表（底稿）'!G9 -> 91.69
B18: 存货周转率(次) | C18: 12.95 | D18: 10.84 | E18: 10.78 | F18: 10.46 | G18: 13.7 | H18: 17.15 | I18: 0.85 | J18: 0.89 | K18: 1.14 | L18: 1.56 | M18: 1.43 | N18: 1.34 | O18: 1.29 | P18: 1.41 | Q18: 1.49 | R18: 1.54 | S18: 1.44 | T18: 1.37 | U18: 1.23 | V18: 1.45 | W18: 1.59 | X18: 1.34 | Y18: 1.09 | Z18: 1.37 | AA18: 1.28 | AB18: 1.16 | AC18: 1.2 | AD18: 1.15 | AE18: 1.24 | AF18: 1.45 | AG18: 15.99 | AH18: 1.27 | AI18: 1.27 | AJ18: 1.27 | AK18: 1.27 | AL18: 1.27 | AS18: 16.34 | AT18: =[5]基础财务数据!AO24/([5]基础财务数据!AN9+[5]基础财务数据!AO9)*2 -> 1.2682314 | AU18: ='[5]主要分析指标表（底稿）'!G8 -> 16.34
A19: 盈利能力 | B19: 主营业务利润率(%) | C19: 14.06 | D19: 17.63 | E19: 13.29 | F19: 6.38 | G19: 16.94 | H19: 17.37 | I19: 8.41 | J19: 9.25 | K19: 10.69 | L19: 17.63 | M19: 23.59 | N19: 22.59 | O19: 20.64 | P19: 19.15 | Q19: 25.09 | R19: 32.34 | S19: 14.32 | T19: -162.33 | U19: 8.01 | V19: 5.23 | W19: 22.37 | X19: 33.65 | Y19: 23.01 | Z19: 25.37 | AA19: 29.74 | AB19: 21.52 | AC19: 16.49 | AD19: 7.21 | AE19: 5.57 | AF19: -11.89 | AG19: 1.37 | AH19: 5.58 | AI19: 5.58 | AJ19: 5.58 | AK19: 5.58 | AL19: 5.58 | AS19: -6.32 | AT19: =([5]基础财务数据!AO21-[5]基础财务数据!AO24-[5]基础财务数据!AO31)/[5]基础财务数据!AO21*100 -> 5.5753991 | AU19: ='[5]主要分析指标表（底稿）'!C32 -> -6.32
B20: 成本费用利润率(%) | C20: 1.12 | D20: 1.81 | E20: 1.9 | F20: -4.91 | G20: 17.65 | H20: 14.43 | I20: 0.31 | J20: 3.32 | K20: 12.4 | L20: 17.79 | M20: 22.37 | N20: 25.9 | O20: 21.41 | P20: 17.95 | Q20: 25.47 | R20: 31.3 | S20: 27.11 | T20: -28.89 | U20: 1.31 | V20: 8.17 | W20: 22.83 | X20: 40.22 | Y20: 26.29 | Z20: 28.91 | AA20: 31.63 | AB20: 16.98 | AC20: 10.01 | AD20: 3.96 | AE20: 0.35 | AF20: -15.75 | AG20: 8.01 | AH20: 2.13 | AI20: 2.13 | AJ20: 2.13 | AK20: 2.13 | AL20: 2.13 | AS20: -1.01 | AT20: =[5]基础财务数据!AO46/([5]基础财务数据!AO23+[5]基础财务数据!AO31+[5]基础财务数据!AO32)*100 -> 2.1280294 | AU20: ='[5]主要分析指标表（底稿）'!C33 -> -1.01
B21: 总资产报酬率(%) | C21: 2.65 | D21: 3.04 | E21: 3.05 | F21: -4.21 | G21: 20.96 | H21: 19.24 | I21: 0.1 | J21: 0.25 | K21: 1.13 | L21: 2.06 | M21: 2.5 | N21: 2.67 | O21: 2.24 | P21: 2.04 | Q21: 2.79 | R21: 3.68 | S21: 2.77 | T21: -1.61 | U21: 0.14 | V21: 0.97 | W21: 2.99 | X21: 4.23 | Y21: 2.33 | Z21: 3.16 | AA21: 3.5 | AB21: 1.75 | AC21: 1.03 | AD21: 0.4 | AE21: 0.04 | AF21: -1.8 | AG21: 2.76 | AH21: 0.23 | AI21: 0.23 | AJ21: 0.23 | AK21: 0.23 | AL21: 0.23 | AS21: -11.13 | AT21: =([5]基础财务数据!AO46+[5]基础财务数据!AO59)/([5]基础财务数据!AO5+[5]基础财务数据!AM5)*2*100 -> 0.22536515 | AU21: ='[5]主要分析指标表（底稿）'!C30 -> -11.13
B22: ROCE（已动用资本回报率）(%) | C22: 3.33 | D22: 4.06 | E22: 3.97 | F22: -5.51 | G22: 27.4 | H22: 28.25 | I22: 0.13 | J22: 0.32 | K22: 1.39 | L22: 2.59 | M22: 3.27 | N22: 3.53 | O22: 3.14 | P22: 2.8 | Q22: 3.87 | R22: 5.21 | S22: 4.28 | T22: -2.18 | U22: 0.19 | V22: 1.31 | W22: 4.27 | X22: 6.04 | Y22: 3.31 | Z22: 4.91 | AA22: 5.33 | AB22: 2.24 | AC22: 1.56 | AD22: 0.59 | AE22: 0.06 | AF22: -2.55 | AG22: -1.73 | AH22: 0.31 | AI22: 0.19 | AJ22: 0.06 | AK22: -2.07 | AL22: -2.15 | AS22: -5.55 | AU22: ='[5]主要分析指标表（底稿）'!G29 -> -5.55
A23: 发展能力 | B23: 总资产增长率(%) | C23: -9.79 | D23: -7.79 | E23: -0.26 | F23: 6.02 | G23: -1.24 | H23: -3.09 | I23: -2.87 | J23: 1.1 | K23: -1.45 | L23: 3.2 | M23: 2.47 | N23: -0.59 | O23: -0.79 | P23: -0.33 | Q23: 0.22 | R23: 2.52 | S23: 3.99 | T23: -8.14 | U23: -0.3 | V23: 0.84 | W23: 3.28 | X23: 1.95 | Y23: 3.32 | Z23: -0.43 | AA23: 1.17 | AB23: 0.86 | AC23: 2.83 | AD23: 2.59 | AE23: 4.53 | AF23: -3.09 | AG23: -4.71 | AH23: =([5]基础财务数据!AO5-[5]基础财务数据!$AM$5)/[5]基础财务数据!$AM$5*100 -> -1.4622606 | AI23: =([5]基础财务数据!AP5-[5]基础财务数据!$AM$5)/[5]基础财务数据!$AM$5*100 -> -2.2491618 | AJ23: =([5]基础财务数据!AQ5-[5]基础财务数据!$AM$5)/[5]基础财务数据!$AM$5*100 -> -4.1252366 | AK23: =([5]基础财务数据!AR5-[5]基础财务数据!$AM$5)/[5]基础财务数据!$AM$5*100 -> -3.1190431 | AL23: =([5]基础财务数据!AS5-[5]基础财务数据!$AM$5)/[5]基础财务数据!$AM$5*100 -> -6.0261533 | AM23: =([5]基础财务数据!AT5-[5]基础财务数据!$AM$5)/[5]基础财务数据!$AM$5*100 -> -100 | AN23: =([5]基础财务数据!AU5-[5]基础财务数据!$AM$5)/[5]基础财务数据!$AM$5*100 -> -100 | AO23: =([5]基础财务数据!AV5-[5]基础财务数据!$AM$5)/[5]基础财务数据!$AM$5*100 -> -100 | ... AR23: =([5]基础财务数据!AY5-[5]基础财务数据!$AM$5)/[5]基础财务数据!$AM$5*100 -> -100 | AS23: -12.05 | AU23: ='[5]主要分析指标表（底稿）'!G24 -> -12.05
B24: 营业收入增长率(%) | C24: 31.86 | D24: -0.12 | E24: -1.57 | F24: -10.15 | G24: 56.43 | H24: 10.62 | I24: 17.23 | J24: 21.61 | K24: 35.66 | L24: 75.21 | M24: 102.6 | N24: 72.87 | O24: 101.06 | P24: 81.56 | Q24: 69.55 | R24: 83.34 | S24: 52.29 | T24: -39.74 | U24: 56.42 | V24: 62.15 | W24: 63.83 | X24: 14.72 | Y24: -15.59 | Z24: 10.37 | AA24: 18.64 | AB24: -8.81 | AC24: -14.8 | AD24: -31.52 | AE24: -14.99 | AF24: 135.36 | AG24: =([5]基础财务数据!AN20-[5]基础财务数据!AA20)/[5]基础财务数据!AA20*100 -> -25.447486 | AH24: =([5]基础财务数据!AO20-[5]基础财务数据!AB20)/[5]基础财务数据!AB20*100 -> -16.418482 | AI24: =([5]基础财务数据!AP20-[5]基础财务数据!AC20)/[5]基础财务数据!AC20*100 -> -25.950112 | AJ24: =([5]基础财务数据!AQ20-[5]基础财务数据!AD20)/[5]基础财务数据!AD20*100 -> -19.342805 | AK24: =([5]基础财务数据!AR20-[5]基础财务数据!AE20)/[5]基础财务数据!AE20*100 -> -12.975486 | AL24: =([5]基础财务数据!AS20-[5]基础财务数据!AF20)/[5]基础财务数据!AF20*100 -> -44.428671 | AM24: =([5]基础财务数据!AT20-[5]基础财务数据!AG20)/[5]基础财务数据!AG20*100 -> -100 | AN24: =([5]基础财务数据!AU20-[5]基础财务数据!AH20)/[5]基础财务数据!AH20*100 -> -100 | ... AR24: =([5]基础财务数据!AY20-[5]基础财务数据!AL20)/[5]基础财务数据!AL20*100 -> -100 | AS24: -24.54 | AU24: ='[5]主要分析指标表（底稿）'!G20 -> -24.54
B25: 营业利润增长率(%) | C25: 111.02 | D25: -74.51 | E25: 486.02 | F25: -418.21 | G25: 477.82 | H25: -10 | I25: 111.4 | J25: 133.9 | K25: 274.29 | L25: 742.57 | M25: 555.83 | N25: 515.53 | O25: 449.22 | P25: 473.43 | Q25: 1990.4 | R25: 1766.06 | S25: 2447.48 | T25: -29.25 | U25: 58.53 | V25: 289.52 | W25: 170.19 | X25: 108.6 | Y25: -7.41 | Z25: 14.71 | AA25: 52.27 | AB25: -15.73 | AC25: -63.75 | AD25: -89.2 | AE25: -98.56 | AF25: 6.55 | AG25: =([5]基础财务数据!AN66-[5]基础财务数据!AA66)/[5]基础财务数据!AA66*100 -> -890.89324 | AH25: =([5]基础财务数据!AO66-[5]基础财务数据!AB66)/[5]基础财务数据!AB66*100 -> -80.935854 | AI25: =([5]基础财务数据!AP66-[5]基础财务数据!AC66)/[5]基础财务数据!AC66*100 -> -95.582935 | AJ25: =([5]基础财务数据!AQ66-[5]基础财务数据!AD66)/[5]基础财务数据!AD66*100 -> -98.892403 | AK25: =([5]基础财务数据!AR66-[5]基础财务数据!AE66)/[5]基础财务数据!AE66*100 -> -159.99277 | AL25: =([5]基础财务数据!AS66-[5]基础财务数据!AF66)/[5]基础财务数据!AF66*100 -> -148.68607 | AM25: =([5]基础财务数据!AT66-[5]基础财务数据!AG66)/[5]基础财务数据!AG66*100 -> -100 | AN25: =([5]基础财务数据!AU66-[5]基础财务数据!AH66)/[5]基础财务数据!AH66*100 -> -100 | ... AR25: =([5]基础财务数据!AY66-[5]基础财务数据!AL66)/[5]基础财务数据!AL66*100 -> -100 | AS25: -126.75 | AU25: ='[5]主要分析指标表（底稿）'!G21 -> -126.75
B26: 资本保值增值率(%) | C26: 136.15 | D26: 113.75 | E26: 100.88 | F26: 89.73 | G26: 140.78 | H26: 120.52
A27: 其他指标 | B27: 利税总额（亿元） | C27: 3.77 | D27: 4.62 | E27: 3.19 | F27: -1.45 | G27: 16.63 | H27: 15.51 | I27: 0.05 | J27: 0.4 | K27: 0.89 | L27: 1.62 | M27: 2 | N27: 1.98 | O27: 1.8 | P27: 1.68 | Q27: 2.19 | R27: 2.98 | S27: 2.08 | T27: -1.03 | U27: 0.21 | V27: 0.89 | W27: 2.59 | X27: 3.11 | Y27: 1.75 | Z27: 2.46 | AA27: 2.55 | AB27: 1.37 | AC27: 0.94 | AD27: 0.44 | AE27: 0.29 | AF27: -1.09 | AG27: =[5]基础财务数据!AN60 -> -0.73 | AH27: =[5]基础财务数据!AO60 -> 0.15 | AI27: =[5]基础财务数据!AP60 -> 0.11 | AJ27: =[5]基础财务数据!AQ60 -> 0.21 | AK27: =[5]基础财务数据!AR60 -> -0.87 | AL27: =[5]基础财务数据!AS60 -> -0.94 | AM27: =[5]基础财务数据!AT60 -> 2.08 | AN27: =[5]基础财务数据!AU60 -> 0 | ... AR27: =[5]基础财务数据!AY60 -> 0 | AS27: -2.18 | AT27: =([5]基础财务数据!AO31+[5]基础财务数据!AO46)/10000 -> 0.145102 | AU27: =([5]基础财务数据!BC31+[5]基础财务数据!BC46)/10000 -> -2.176551
B28: 经济增加值EVA（亿元) | C28: 1.05 | D28: -0.31 | E28: -1.24 | F28: -3.95 | G28: 10.25 | H28: 8.82 | I28: -1.22 | J28: -1.06 | K28: -0.31 | L28: 1 | M28: 2.61 | N28: 4.32 | O28: ='[6]eva roce(底稿）'!B5/100000000 -> 11.842427 | P28: 5.89 | Q28: 7.65 | R28: 9.99 | S28: 11.81 | T28: 10.16 | U28: -1.75 | V28: -1.13 | W28: 0.46 | X28: 2.72 | Y28: 4.19 | Z28: 5.79 | AA28: 7.69 | AB28: 8.65 | AC28: 9.26 | AD28: 9.58 | AE28: 9.7 | AF28: 8.82 | AG28: -2.95 | AH28: -2.07 | AI28: -2.11 | AJ28: -2 | AK28: -2.84 | AL28: -2.89 | AS28: -2.95 | AU28: ='[5]主要分析指标表（底稿）'!G28/10000/10000 -> -2.9532088
B29: 挖潜增效（万元） | C29: 9847 | D29: 5724 | E29: 7796 | F29: 15122 | G29: 12086 | H29: 12557 | I29: 841 | J29: 709 | K29: 1015 | L29: 1092 | M29: 1420 | N29: 1501 | O29: 1334 | P29: 1255 | Q29: 904 | R29: 1058 | S29: 675 | T29: 283 | U29: 676 | V29: 731 | W29: 798 | X29: 669 | Y29: 663 | Z29: 2171 | AA29: 2987 | AB29: 951 | AC29: 761 | AD29: 698 | AE29: 975 | AF29: 477 | AG29: 338 | AH29: 526 | AI29: 756 | AJ29: 599 | AK29: 758 | AL29: 522 | AS29: 3499
B30: “两金”占用（亿元） | C30: 4 | D30: 4.91 | E30: 4.52 | F30: 4.67 | G30: 5.01 | H30: 4.18 | I30: 4.71 | J30: 5.39 | K30: 4.41 | L30: 4.54 | M30: 4.66 | N30: 4.79 | O30: 4.85 | P30: 4.52 | Q30: 4.07 | R30: 4.63 | S30: 5.44 | T30: 5.01 | U30: 4.33 | V30: 4.35 | W30: 4.45 | X30: 4.63 | Y30: 5.16 | Z30: 4.85 | AA30: 5.72 | AB30: 5.57 | AC30: 5.26 | AD30: 5.94 | AE30: 6.05 | AF30: 4.18 | AH30: 5.82 | AI30: 6.08 | AJ30: 5.97 | AK30: 6.07 | AL30: 5.65 | AS30: 5.65 | AT30: =('[5]资产负债、利润（底稿）'!C11+'[5]资产负债、利润（底稿）'!C17)/10000/10000 -> 5.6516436 | AU30: =AT30 -> 5.6516436
B31: “两金”占用占流动资产比重（%） | C31: 85.11 | D31: 78.69 | E31: 69.97 | F31: 53.46 | G31: 76.46 | H31: 49.85 | I31: 65.66 | J31: 68 | K31: 63.84 | L31: 55.53 | M31: 49.4 | N31: 57.7 | O31: 55.07 | P31: 53.75 | Q31: 50.98 | R31: 48.84 | S31: 42.55 | T31: 76.46 | U31: 67.44 | V31: 62.47 | W31: 51.59 | X31: 57.9 | Y31: 55.82 | Z31: 45.32 | AA31: 40.65 | AB31: 46.84 | AC31: 40.71 | AD31: 47.47 | AE31: 48.35 | AF31: 49.85 | AG31: 0 | AH31: 72.45 | AI31: 76.89 | AJ31: 85.28 | AK31: 81.52 | AL31: 83.99 | AS31: 67.38 | AT31: =('[5]资产负债、利润（底稿）'!C11+'[5]资产负债、利润（底稿）'!C17)/'[5]资产负债、利润（底稿）'!C22*100 -> 83.988765 | AU31: =AU30/'[5]主要分析指标表（底稿）'!O44*1000000 -> 67.398038
B32: 人工成本利润率（%） | C32: 12.15 | D32: 17.41 | E32: 17.99 | F32: -47.39 | G32: 193.2 | H32: 162.35 | I32: 2.83 | J32: 35.72 | K32: 104.32 | L32: 114.34 | M32: 97.96 | N32: 259.41 | O32: 219.89 | P32: 155.13 | Q32: 377.59 | R32: 355.05 | S32: -346.51 | T32: 394.35 | U32: 10.39 | V32: 66.62 | W32: 114.45 | X32: 434.35 | Y32: 294.93 | Z32: 437.97 | AA32: 391.05 | AB32: 152.94 | AC32: 102.11 | AD32: 110.37 | AE32: 45.55 | AF32: -1086.66 | AG32: =[5]基础财务数据!AN46*10000/('[5]劳动生产率（底稿）'!D20-'[5]劳动生产率（底稿）'!C20)*100 -> -27.964841 | AH32: 57.86 | AI32: 18.2 | AJ32: 3.67 | AK32: -128.99 | AL32: -143.76 | AS32: -143.76 | AT32: ='[5]资产负债、利润（底稿）'!C84/'[5]劳动生产率（底稿）'!C20*100 -> -143.76453 | AU32: ='[5]资产负债、利润（底稿）'!C84/'[5]劳动生产率（底稿）'!C20*100 -> -143.76453
