Workbook
Name _Fill: #REF!
Name _Fill: #REF!
Name _Fill: #REF!
Name _Order1: 255
Name XLRPARAMS_GCMC: #REF!
Name XLRPARAMS_GCMC: #REF!
Name XLRPARAMS_GCMC: #REF!

Sheet 封面
A7: 2021年4月
A8: 项目月度商务管理报表
A10: 工程
A27: 潘达建工集团有限公司
A28: 综合工程履约中心
A29: 编制时间： 年 月 日

Sheet 目录
A1: 目 录
A2: 封面····································································································································· | B2: 封面 | C2: 不填写
A3: 目录····················································································································································· | B3: 目录 | C3: 不填写
A4: 编制说明·············································································································································· | B4: 说明 | C4: 不填写
A5: 项目月度资金预算批复单······································································································································· | B5: 表1 | C5: 部分填写
A6: 项目月度成本管理分析········································································································································ | B6: 表2 | C6: 部分填写
A7: 项目级商务报表汇总表········································································································································ | B7: 表3 | C7: 不填写
A8: 业主产值详表······························································································································· | B8: 表3.1 | C8: 填写
A9: 业主待确产值详表········································································································································ | B9: 表3.1.1 | C9: 填写
A10: 月度成本、资金详表····································································································································· | B10: 表3.2 | C10: 填写
A11: 已发生待确成本计算详表········································································································································ | B11: 表3.2.1 | C11: 填写

Sheet 编制说明
A1: 编 制 说 明
A2: 1、商务报表统计的范围： 在建项目（存量在建、新增在建）、完工未结（指业主未办理结算），完工已结（指业主当年办理结算的项目）。当年完工已结项目当年报表中不予删除，于次年1月报表中更新删除，并在1月报表总结中说明。
A3: 2、填报时间： 1）项目部编制产值、结算金额每月26日完成更新报送区域公司及集团，集团28日审核完成并移交集团财务中心。 2）项目部更新业主已收款、内部已付款、间接费、税金、管理费等相关财务数据次月7日完成并移交集团财税中心，集团财税中心次月8日审核完成并移交集团履约中心。 3）集团履约中心在次月15日审核汇总后呈报集团总经理。
A4: 3、档案管理要求： 3.1每月完整的电子文档保存； 3.2 需打印的文件：月度商务管理分析表、月度商务管理汇总表。
A5: 4、项目成本管理警示： 4.1 7项指标项，超过6项（含6项）超出参考范围值或总利润率连续3个月以上（含3个月）为负，则本项目为红色预警； 4.2 7项指标项，2-5项（含5项）超出参考范围值或总利润率连续2个月（含2个月）为负，则本项目为黄色预警； 4.3 指标项正常及利润率为正，则项目运行良好，显示绿灯。

Sheet 项目月度资金预算批复单-表1
A1: 表1 - 月度资金预算批复单
A2: 项目名称: | D2: 报告期间: | F2: 单位:元
A3: 工程名称 | B3: ='项目月度商务管理汇总表-表3'!B7 -> 0 | E3: 合同额 | F3: ='项目月度商务管理汇总表-表3'!S7 -> 0
A4: 一、资金情况
A5: 自开工累计总收入 | B5: ='项目月度商务管理汇总表-表3'!BM7 -> 0 | C5: 其中：业主收入 | D5: ='项目月度商务管理汇总表-表3'!BU7 -> 0 | E5: 其中：往来收入 | F5: ='项目月度商务管理汇总表-表3'!CC7+'项目月度商务管理汇总表-表3'!CG7+'项目月度商务管理汇总表-表3'!CH7 -> 0
A6: 自开工累计总支出 | B6: ='项目月度商务管理汇总表-表3'!CI7 -> 0 | C6: 其中：成本支出 | D6: ='项目月度商务管理汇总表-表3'!CU7 -> 0 | E6: 其中：往来支出 | F6: ='项目月度商务管理汇总表-表3'!CZ7+'项目月度商务管理汇总表-表3'!DD7+'项目月度商务管理汇总表-表3'!DE7 -> 0
A7: 公司垫资本金 | B7: =IF(LOOKUP(1,0/(项目收支汇总表!A5:A306="1"),项目收支汇总表!C5:C306)>=0,0,ABS(LOOKUP(1,0/(项目收支汇总表!A5:A306="1"),项目收支汇总表!C5:C306))-D7) -> 0 | C7: 公司垫资利息 | D7: =LOOKUP(1,0/(项目收支汇总表!A5:A306="3.3.1"),项目收支汇总表!C5:C306) -> 0 | F7: =""
A8: 期初资金流（总收入-总支出） | B8: ='项目月度商务管理汇总表-表3'!DF7 -> 0 | C8: 期初项目经营性资金流（业主收款-成本支出） | D8: ='项目月度商务管理汇总表-表3'!DG7 -> 0 | E8: 期初往来资金余额 | F8: =F5-F6 -> 0
A9: 应收未收款 （合约） | B9: ='项目月度商务管理汇总表-表3'!AL7 -> 0 | C9: 应付未付款 （合约） | D9: ='项目月度商务管理汇总表-表3'!AW7 -> 0 | F9: =""
A10: 资金收款计划 | B10: ='项目月度商务管理汇总表-表3'!DJ7 -> 0 | C10: 其中：业主收入 | D10: ='项目月度商务管理汇总表-表3'!DH7 -> 0 | E10: 其中：往来收入 | F10: ='项目月度商务管理汇总表-表3'!DI7 -> 0
A11: 项目资金支出计划 | B11: ='项目月度商务管理汇总表-表3'!DM7 -> 0 | C11: 其中：成本支出 | D11: ='项目月度商务管理汇总表-表3'!DK7 -> 0 | E11: 其中：往来支出 | F11: ='项目月度商务管理汇总表-表3'!DL7 -> 0
A12: 公司批准资金支出 | B12: ='项目月度商务管理汇总表-表3'!DP7 -> 0 | C12: 其中：成本支出 | D12: ='项目月度商务管理汇总表-表3'!DN7 -> 0 | E12: 其中：往来支出 | F12: ='项目月度商务管理汇总表-表3'!DO7 -> 0
A13: 预计期末资金流 （总收入-总支出） | B13: =B8+B10-B12 -> 0 | C13: 预计期末项目经营性资金流（业主收款-成本支出） | D13: =D8+D10-D12 -> 0 | E13: 预计期末往来资金余额 | F13: =F8+F10-F12 -> 0
A14: 二、项目利润状况
A15: 业主产值 （已确认） | B15: ='项目月度商务管理汇总表-表3'!AE7 -> 0 | C15: 全口径成本（已确认） | D15: ='项目月度商务管理汇总表-表3'!AN7 -> 0 | E15: 开累至今利润额 （已确） | F15: ='项目月度商务管理汇总表-表3'!BD7 -> 0
A16: 业主产值 （已确认+待确认） | B16: ='项目月度商务管理汇总表-表3'!AG7 -> 0 | C16: 全口径成本（已确认+待确认） | D16: ='项目月度商务管理汇总表-表3'!AP7 -> 0 | E16: 开累至今利润额 （已确+待确） | F16: ='项目月度商务管理汇总表-表3'!BB7 -> 0
A17: 三、项目各指标分析
A18: 指标名称 | B18: 计算规则 | C18: 结果 | D18: 参考值 | E18: 红绿灯 | F18: 存在问题原因分析
A20: ="[10]业主产值确权比" -> [10]业主产值确权比 | B20: ="已确权产值/总产值" -> 已确权产值/总产值 | C20: ='项目月度商务管理汇总表-表3'!BF7 -> #DIV/0! | D20: ="主要根据合同约定，常规值≥85%" -> 主要根据合同约定，常规值≥85% | E20: 绿
A21: ="[20]确权产值回款率" -> [20]确权产值回款率 | B21: ="业主已收款/已确权产值" -> 业主已收款/已确权产值 | C21: ='项目月度商务管理汇总表-表3'!BG7 -> #DIV/0! | D21: ="主要根据合同约定，常规值≥75~80%" -> 主要根据合同约定，常规值≥75~80% | E21: 绿
A22: ="[30]成本确权比" -> [30]成本确权比 | B22: ="已确权产值/总成本" -> 已确权产值/总成本 | C22: ='项目月度商务管理汇总表-表3'!BH7 -> #DIV/0! | D22: ="主要根据合同约定，常规值≥85%" -> 主要根据合同约定，常规值≥85% | E22: 绿
A23: [40]成本刚性度 | B23: ="已确权成本/总成本" -> 已确权成本/总成本 | C23: ='项目月度商务管理汇总表-表3'!BI7 -> #DIV/0! | D23: ="≥95%" -> ≥95% | E23: 绿
A24: ="[50]产值现金流入比" -> [50]产值现金流入比 | B24: ="总收入/总产值" -> 总收入/总产值 | C24: ='项目月度商务管理汇总表-表3'!BJ7 -> #DIV/0! | D24: ="≥70%" -> ≥70% | E24: 绿
A25: ="[60]成本资金收入比" -> [60]成本资金收入比 | B25: ="总收入/总成本" -> 总收入/总成本 | C25: ='项目月度商务管理汇总表-表3'!BK7 -> #DIV/0! | D25: ="主要根据合同约定判断" -> 主要根据合同约定判断 | E25: 绿
A26: ="[70]成本资金支出比" -> [70]成本资金支出比 | B26: ="总支出/总成本" -> 总支出/总成本 | C26: ='项目月度商务管理汇总表-表3'!BL7 -> #DIV/0! | D26: ="65%~80%" -> 65%~80% | E26: 绿

Sheet 项目月度商务管理分析表-表2
A1: 表2 - 项目商务管理分析表
A2: 项目名称: | G2: 报告期间: | M2: 单位:元
A3: 一、项目总体评价：
A4: 上缴管理费费率 | B4: ='项目月度完全成本、付款明细表-表3.2'!P2 -> 0.03 | D4: 预计完工应缴纳管理费 | E4: =B4*D15 -> 0 | G4: 已缴纳管理费 | H4: ='项目月度商务管理汇总表-表3'!CT7 -> 0 | J4: 欠公司管理费 | L4: ='项目月度商务管理汇总表-表3'!BN7*B4-H4 -> 0
A5: 开累至今利润额（已确+待确） | B5: ='项目月度商务管理汇总表-表3'!BB7 -> 0 | D5: 利润率 （已确+待确） | E5: ='项目月度商务管理汇总表-表3'!BC7 -> #DIV/0! | G5: 开累至今利润额（已确） | H5: ='项目月度商务管理汇总表-表3'!BD7 -> 0 | J5: 利润率 （已确） | L5: ='项目月度商务管理汇总表-表3'!BE7 -> #DIV/0!
A6: 项目预警（红 黄 绿）： | D6: 绿 | E6: 此处填写预警存在问题及原因分析
A7: 二、工程概况：
A8: 工程名称： | D8: ='项目月度商务管理汇总表-表3'!B7 -> 0
A9: 建设单位名称： | D9: ='项目月度商务管理汇总表-表3'!U7 -> 0
A10: 工程地点： | H10: 工程规模： | J10: ='项目月度商务管理汇总表-表3'!L7 -> 0
A11: 合同开工时间： | H11: 合同竣工时间：
A12: 实际开工时间: | H12: 实际竣工时间:
A13: 合同价款（不包括暂列金额、暂估价、甲供材）： | D13: ='项目月度商务管理汇总表-表3'!T7 -> 0 | H13: 单方造价（元/m2） | J13: =D13/J10 -> #DIV/0!
A14: 工程款支付方式： | H14: 工程资金来源：
A15: 预估完工结算金额 ： | H15: 本年度目标产值（已确+待确）：
A16: 三、工程形象进度简要概况：
A18: 四、各项商务数据风险清单状况
A19: 项目名称 | B19: 风险因素 | D19: 结果 | F19: 参考值 | H19: 红绿灯 | I19: 存在问题原因分析 | K19: 改进措施及风险防控 | M19: 备 注
A21: 进度 | B21: [110]开累产值完成额 | D21: ='项目月度商务管理汇总表-表3'!AG7 -> 0 | H21: 绿
B22: [120]开累产值完成率 | D22: =D21/D15 -> #DIV/0! | F22: 是否有滞后现象 | H22: 绿
B23: [130]本年度产值完成额 | D23: ='项目月度商务管理汇总表-表3'!AA7 -> 0 | H23: 绿
B24: [140]本年度产值完成率 | D24: =D23/J15 -> #DIV/0! | F24: 是否有滞后现象 | H24: 绿
A25: 利润 | B25: [210]开累至今利润额 （已确+待确） | D25: ='项目月度商务管理汇总表-表3'!BB7 -> 0 | F25: ≥±300万元（在建项目）；≥目标利润额（完工项目） | H25: 绿
B26: [220]利润率（%） （已确+待确） | D26: ='项目月度商务管理汇总表-表3'!BC7 -> #DIV/0! | F26: ≥±5%（在建项目）；≥目标利润率（完工项目） | H26: 绿
B27: [223]利润额 已确产值-(已确成本+待确成本) | D27: ='项目月度商务管理汇总表-表3'!AE7-'项目月度商务管理汇总表-表3'!AN7-'项目月度商务管理汇总表-表3'!AO7 -> 0 | F27: ≥±100万元（在建项目）；≥目标利润额（完工项目） 受确权产值影响，需根据合同约定具体分析 | H27: 绿
B28: [225]利润率(%)[已确产值-(已确成本+待确成本)]/已确产值 | D28: =('项目月度商务管理汇总表-表3'!AE7-'项目月度商务管理汇总表-表3'!AN7-'项目月度商务管理汇总表-表3'!AO7)/'项目月度商务管理汇总表-表3'!AE7 -> #DIV/0! | F28: ≥±15%（在建项目）；≥目标利润率（完工项目）受确权产值影响，需根据合同约定具体分析 | H28: 绿
B29: [230]开累至今利润额 （已确） | D29: ='项目月度商务管理汇总表-表3'!BD7 -> 0 | F29: ≥±500万元（在建项目）；≥目标利润额（完工项目） | H29: 绿
B30: [240]利润率（%） （已确） | D30: ='项目月度商务管理汇总表-表3'!BE7 -> #DIV/0! | F30: ≥±10%（在建项目；≥目标利润率（完工项目） | H30: 绿
A31: 造价管理 | B31: [310]施工图预算 | F31: 1.是否按要求时间办理； 2.是否存在重大争议项 | H31: 绿
B32: [320]签证、索赔办理情况 | F32: 描述办理情况及完成率； | H32: 绿
B33: [330]认质认价办理情况 | F33: 描述办理情况及完成率； | H33: 绿
B34: [340]业主结算 | F34: 1.是否按要求时间办理； 2.是否存在重大争议项 | H34: 绿
B35: [350]目标成本 | F35: 1.是否完成； 2.是否在目标管理范围内 | H35: 绿
B36: [360]完工成本预分析 | F36: 1.是否完成； 2.是否达到利润目标； | H36: 绿
A37: 五、主控费用状况
A38: 项目名称 | B38: 范围 | C38: 目标成本 | E38: 合同(已签订） | G38: 实际发生 | K38: 红绿灯 | L38: 存在问题及改进措施 | M38: 备 注
C39: 金额 | D39: 单方造价 | E39: 金额 | F39: 单方造价 | G39: 金额 | H39: 单方造价 | I39: 其中：已确认金额 | J39: 单方造价
A41: [10]周转材费用 | B41: 模板、木枋、架管、扣件、矩管、铝模、爬架等 | D41: =C41/$J$10 -> #DIV/0! | F41: =E41/$J$10 -> #DIV/0! | H41: =G41/$J$10 -> #DIV/0! | J41: =I41/$J$10 -> #DIV/0! | K41: 绿 | L41: 1.存在问题： 2.改进措施：
A42: [20]垂直运输费用 | B42: 塔吊、施工电梯、物料提升机等 | D42: =C42/$J$10 -> #DIV/0! | F42: =E42/$J$10 -> #DIV/0! | H42: =G42/$J$10 -> #DIV/0! | J42: =I42/$J$10 -> #DIV/0! | K42: 绿 | L42: 1.存在问题： 2.改进措施：
A43: [30]土建劳务费用 | D43: =C43/$J$10 -> #DIV/0! | F43: =E43/$J$10 -> #DIV/0! | H43: =G43/$J$10 -> #DIV/0! | J43: =I43/$J$10 -> #DIV/0! | K43: 绿 | L43: 1.存在问题： 2.改进措施：
A44: [40]安全文明费用 | B44: 临时设施、安全、文明、环境保护 | D44: =C44/$J$10 -> #DIV/0! | F44: =E44/$J$10 -> #DIV/0! | H44: =G44/$J$10 -> #DIV/0! | J44: =I44/$J$10 -> #DIV/0! | K44: 绿 | L44: 1.存在问题： 2.改进措施：
A45: [50]水电费用 | D45: =C45/$J$10 -> #DIV/0! | F45: =E45/$J$10 -> #DIV/0! | H45: =G45/$J$10 -> #DIV/0! | J45: =I45/$J$10 -> #DIV/0! | K45: 绿 | L45: 1.存在问题： 2.改进措施：
A46: [60]间接费用 | D46: =C46/$J$10 -> #DIV/0! | F46: =E46/$J$10 -> #DIV/0! | H46: =G46/$J$10 -> #DIV/0! | J46: =I46/$J$10 -> #DIV/0! | K46: 绿 | L46: 1.存在问题： 2.改进措施：
A47: 说明:1.周转材料费用不包含人工费，但从合同计算依据出发，铝模、爬架为专业分包时，简化处理该部分包含人工费，备注中注明； 2.垂直运输费用包含但不限于进出场费、租赁费、人工费等，但不包含基础费用； 3.土建劳务费用包含但不限于主体、二次结构、粗装修等，铝模、爬架不是专业分包时，需将该部分人工费进入土建劳务费用，备注中注明； 4.安全文明费用包含但不限于临时设施、安全、文明、环境保护；

Sheet 项目月度商务管理汇总表-表3
A1: 表3 - 项目月度商务管理汇总表
A2: 项目名称: | H2: 报告期间: | DS2: 单位:元
A3: 序号 | B3: 工程名称 | C3: 基 本 信 息 | V3: 业主产值 | AH3: 业主收款 | AN3: 全口径成本 | AU3: 应付未付款 | BB3: 利润 （自开工累计） | BF3: 指标 | BM3: 总收入 | CI3: 总支出 | DF3: 期初资金余额 | DH3: 资金计划 | DQ3: 预计期末资金余额 | DS3: 备注
C4: 客户体系 | D4: 项目状态 | E4: 增/存量 | F4: 管理费率 | G4: 专业 | H4: 大客户 | I4: 经营模式 | J4: 合伙人 | K4: 区域 | L4: 工程规模 | M4: 计划开工时间 | N4: 计划竣工时间 | O4: 实际开工日期 | P4: 实际竣工日期 | Q4: 合同编号 （PKPM编号） | R4: 合同名称 | S4: 合同金额 （包括暂列金额、暂估价、甲供材） | T4: 合同金额 （不包括暂列金额、暂估价、甲供材） | U4: 甲方名称 | V4: 开工至上年度产值 | Y4: 本年度累计实际完成产值 | AB4: 其中:本月实际完成产值 | AE4: 自开工累计实际完成产值 | AH4: 应收工程款 （合约） | AJ4: 已收工程款 | AL4: 应收未收款 （合约） | AM4: 应收未收款 (100%) | AN4: 自开工累计已发生成本（完全成本） | AR4: 其中: 本月已发生成本（完全成本） | AU4: 合约 | AV4: 已付款 | AW4: 应付未付款 （合约） | AY4: 100% | BA4: 应付未付款 (100%) | BB4: 总产值-总成本 | BD4: 已确产值-已确成本 | BF4: 业主产值确权比（%） | BG4: 确权产值回款率（%） | BH4: 成本确权比 | BI4: 成本刚性度 | BJ4: 产值现金流入比 | BK4: 成本资金收入比 | BL4: 成本资金支出比 | BM4: 收入合计 （总） | BN4: 业主收款 | BX4: 借款收入 | CD4: 保证金收入 | CH4: 其他收入 | CI4: 支出合计 （总） | CJ4: 成本支出 | CV4: 借款本金返还 | DA4: 保证金支出 | DE4: 项目往来借支款 | DF4: 资金流 | DG4: 项目经营性资金流 | DH4: 资金收款计划 | DK4: 项目资金支出计划 | DN4: 公司批准资金支出 | DQ4: 资金流 | DR4: 项目经营性资金流
V5: 业主已确认 | W5: 业主待确认 | X5: 合计 | Y5: 业主已确认 | Z5: 业主待确认 | AA5: 合计 | AB5: 业主已确认 | AC5: 业主待确认 | AD5: 合计 | AE5: 业主已确认 | AF5: 业主待确认 | AG5: 合计 | AH5: 累计应收工程款 | AI5: 应收比例（%） | AJ5: 累计已收工程款 | AK5: 收款比例（%） | AL5: 应收未收款 （合约） | AN5: 已确认 | AO5: 待确认 | AP5: 合计 | AQ5: 其中:人工费 | AR5: 已确认 | AS5: 待确认 | AT5: 合计 | AU5: 应付款 （合约） | AV5: 已付款 | AW5: 应付未付款 （合约） | AX5: 其中：应付未付款人工费（100%） | AY5: 应付未付款 （不含待确成本） | AZ5: 应付未付款 （待确成本） | BA5: 小计 | BB5: 利润额 | BC5: 利润率 （%） | BD5: 利润额 | BE5: 利润率 （%） | BF5: 已确认产值/总产值 | BG5: 业主已收款/已确认产值 | BH5: 已确认产值/总成本 | BI5: 已确认成本/总成本 | BJ5: 总收入/总产值 | BK5: 总收入/总成本 | BL5: 总支出/总成本 | BN5: 业主计量收入 | BO5: 业主代扣代缴 | BP5: 奖罚款 | BQ5: 甲指分包 | BR5: 甲供材 | BS5: 总包管理费收入 | BT5: 其他收入 | BU5: 业主收款小计 | BV5: 其中：抵房 | BW5: 其中：专户收入 | BX5: 公司现金借款 | BY5: 公司票据借款 | BZ5: 内部项目资金拆借收入 | CA5: 自筹往来款 | CB5: 公司结算中心存款利息收入 | CC5: 借款小计 | CD5: 收取分供方保证金 | CE5: 业主保证返还收入 | CF5: 其他保证金收入 | CG5: 保证金小计 | CH5: 其他收入 | CJ5: 劳务分包 | CK5: 专业分包 | CL5: 材料、设备 | CM5: 机械设备租赁 | CN5: 周转材料租赁 | CO5: 安全文明施工费 | CP5: 其他直接费 | CQ5: 间接成本 | CR5: 财务成本 | CS5: 税金 | CT5: 公司管理费 | CU5: 成本支出小计 | CV5: 内部项目资金拆借本金返还支出 | CW5: 公司借款本金返还支出 | CX5: 公司借票据返还（兑付） | CY5: 自筹往来款返还支出 | CZ5: 小计 | DA5: 分供方保证金返还支出 | DB5: 业主保证金支出 | DC5: 其他保证金支出 | DD5: 小计 | DE5: 项目往来借支款（包括项目部备用金） | DF5: 总收入-总支出 | DG5: 业主收款-成本支出 | DH5: 业主收款 | DI5: 往来收入 | DJ5: 小计 | DK5: 成本支出 | DL5: 往来支出 | DM5: 小计 | DN5: 成本支出 | DO5: 往来支出 | DP5: 小计 | DQ5: 总收入-总支出 | DR5: 业主收款-成本支出
A6: 计算编号 | V6: 1.1 | W6: 1.2 | X6: 1.3=1.1+1.2 | Y6: 1.4=1.10-1.1 | Z6: 1.5=1.11-1.2 | AA6: 1.6=1.4+1.5 | AB6: 1.7 | AC6: 1.8 | AD6: 1.9=1.7+1.8 | AE6: 1.10 | AF6: 1.11 | AG6: 1.12=1.10+1.11 | AH6: 2.1 | AI6: 2.2=2.1/1.10 | AJ6: 2.3 | AK6: 2.4=2.3/1.10 | AL6: 2.5=2.1-2.3 | AM6: 2.6=1.10-2.3 | AN6: 3.1 | AO6: 3.2 | AP6: 3.3=3.1+3.2 | AQ6: 3.3.1 | AR6: 3.4 | AS6: 3.5 | AT6: 3.6=3.4+3.5 | AU6: 4.1 | AV6: 4.2 | AW6: 4.3=4.1-4.2 | AX6: 4.4 | AY6: 4.5 | AZ6: 4.6 | BA6: 4.7 | BB6: 5.1=1.12-3.3 | BC6: 5.2=5.1/1.12 | BD6: 5.3=1.10-3.1 | BE6: 5.4=5.3/1.10 | BF6: 6.1=1.10/1.12 | BG6: 6.2=2.3/1.10 | BH6: 6.3=1.10/3.3 | BI6: 6.4=3.1/3.3 | BJ6: 6.5=7.1/1.12 | BK6: 6.6=7.1/3.3 | BL6: 6.7=8.1/3.3 | BM6: 7.1=7.2+7.3+7.4+7.5 | BN6: 7.2.1 | BO6: 7.2.2 | BP6: 7.2.3 | BQ6: 7.2.4 | BR6: 7.2.5 | BS6: 7.2.6 | BT6: 7.2.7 | BU6: 7.2=7.2.1+...+7.2.7 | BV6: 7.2.8 | BW6: 7.2.9 | BX6: 7.3.1 | BY6: 7.3.2 | BZ6: 7.3.3 | CA6: 7.3.4 | CB6: 7.3.5 | CC6: 7.3=7.3.1+...+7.3.5 | CD6: 7.4.1 | CE6: 7.4.2 | CF6: 7.4.3 | CG6: 7.4=7.4.1+...+7.4.3 | CH6: 7.5 | CI6: 8.1=8.2+...+8.5 | CJ6: 8.2.1 | CK6: 8.2.2 | CL6: 8.2.3 | CM6: 8.2.4 | CN6: 8.2.5 | CO6: 8.2.6 | CP6: 8.2.7 | CQ6: 8.2.8 | CR6: 8.2.9 | CS6: 8.2.10 | CT6: 8.2.11 | CU6: 8.2=8.2.1+...+8.2.11 | CV6: 8.3.1 | CW6: 8.3.2 | CX6: 8.3.3 | CY6: 8.3.4 | CZ6: 8.3=8.3.1+...+8.3.4 | DA6: 8.4.1 | DB6: 8.4.2 | DC6: 8.4.3 | DD6: 8.4.4=8.4.1+...8.4.3 | DE6: 8.5 | DF6: 9.1=7.1-8.1 | DG6: 9.2=7.2-8.2 | DH6: 10.1 | DI6: 10.2 | DJ6: 10.3=10.1+10.2 | DK6: 10.4 | DL6: 10.5 | DM6: 10.6=10.4+10.5 | DN6: 10.7 | DO6: 10.8 | DP6: 10.9=10.7+10.8 | DQ6: 11.1=9.1+10.3-10.9或10.6 | DR6: 11.2=9.2+10.1-10.7或10.4
F7: =LOOKUP(1,0/(项目收支汇总表!A5:A306="5.1"),项目收支汇总表!C5:C306) -> 0.03 | V7: ='项目月度业主产值表-表3.1'!D6 -> 0 | W7: ='项目月度业主产值表-表3.1'!E6 -> 0 | X7: =V7+W7 -> 0 | Y7: ='项目月度业主产值表-表3.1'!G6 -> 0 | Z7: ='项目月度业主产值表-表3.1'!H6 -> 0 | AA7: =Y7+Z7 -> 0 | AB7: ='项目月度业主产值表-表3.1'!J6 -> 0 | AC7: ='项目月度业主产值表-表3.1'!K6 -> 0 | AD7: =AB7+AC7 -> 0 | AE7: ='项目月度业主产值表-表3.1'!M6 -> 0 | AF7: ='项目月度业主产值表-表3.1'!N6 -> 0 | AG7: =AE7+AF7 -> 0 | AH7: ='项目月度业主产值表-表3.1'!P6 -> 0 | AI7: =AH7/AE7 -> #DIV/0! | AJ7: =BU7 -> 0 | AK7: =AJ7/AE7 -> #DIV/0! | AL7: =AH7-AJ7 -> 0 | AM7: =AE7-AJ7 -> 0 | AN7: ='项目月度完全成本、付款明细表-表3.2'!N69 -> 0 | AO7: ='项目月度完全成本、付款明细表-表3.2'!O69 -> 0 | AP7: =AN7+AO7 -> 0 | AQ7: ='项目月度完全成本、付款明细表-表3.2'!Q7 -> 0 | AR7: ='项目月度完全成本、付款明细表-表3.2'!R69 -> 0 | AS7: ='项目月度完全成本、付款明细表-表3.2'!S69 -> 0 | AT7: =AR7+AS7 -> 0 | AU7: ='项目月度完全成本、付款明细表-表3.2'!V69 -> 0 | AV7: ='项目月度完全成本、付款明细表-表3.2'!X69 -> 0 | AW7: =AU7-AV7 -> 0 | AX7: ='项目月度完全成本、付款明细表-表3.2'!AA7 -> 0 | AY7: ='项目月度完全成本、付款明细表-表3.2'!AB7 -> 0 | AZ7: ='项目月度完全成本、付款明细表-表3.2'!AC7 -> 0 | BA7: ='项目月度完全成本、付款明细表-表3.2'!AD7 -> 0 | BB7: =AG7-AP7 -> 0 | BC7: =BB7/AG7 -> #DIV/0! | BD7: =AE7-AN7 -> 0 | BE7: =BD7/AE7 -> #DIV/0! | BF7: =AE7/AG7 -> #DIV/0! | BG7: =AJ7/AE7 -> #DIV/0! | BH7: =AE7/AP7 -> #DIV/0! | BI7: =AN7/AP7 -> #DIV/0! | BJ7: =BM7/AG7 -> #DIV/0! | BK7: =BM7/AP7 -> #DIV/0! | BL7: =CI7/AP7 -> #DIV/0! | BM7: =BU7+CC7+CG7+CH7 -> 0 | BN7: =LOOKUP(1,0/(项目收支汇总表!A5:A20="2.1"),项目收支汇总表!C5:C20)+LOOKUP(1,0/(项目收支汇总表!A5:A20="2.3"),项目收支汇总表!C5:C20) -> 0 | BO7: =LOOKUP(1,0/(项目收支汇总表!A5:A306="2.2"),项目收支汇总表!C5:C306) -> 0 | BP7: =LOOKUP(1,0/(项目收支汇总表!A5:A306="2.6"),项目收支汇总表!C5:C306) -> 0 | BQ7: =LOOKUP(1,0/(项目收支汇总表!A5:A306="2.4"),项目收支汇总表!C5:C306) -> 0 | BR7: =LOOKUP(1,0/(项目收支汇总表!A5:A306="2.5"),项目收支汇总表!C5:C306) -> 0 | BS7: =LOOKUP(1,0/(项目收支汇总表!A5:A306="2.7"),项目收支汇总表!C5:C306) -> 0 | BT7: =LOOKUP(1,0/(项目收支汇总表!A5:A306="2.8"),项目收支汇总表!C5:C306) -> 0 | BU7: =SUM(BN7:BT7) -> 0 | BV7: =LOOKUP(1,0/(项目收支汇总表!A5:A306="2.1.1"),项目收支汇总表!C5:C306) -> 0 | BW7: =LOOKUP(1,0/(项目收支汇总表!A5:A306="2.1.3"),项目收支汇总表!C5:C306) -> 0 | BX7: =LOOKUP(1,0/(项目收支汇总表!A5:A306="2.10.1"),项目收支汇总表!C5:C306)+LOOKUP(1,0/(项目收支汇总表!A5:A306="2.10.4"),项目收支汇总表!C5:C306) -> 0 | BY7: 0 | BZ7: =LOOKUP(1,0/(项目收支汇总表!A5:A306="2.9.1"),项目收支汇总表!C5:C306)+LOOKUP(1,0/(项目收支汇总表!A5:A306="2.9.4"),项目收支汇总表!C5:C306) -> 0 | CA7: =LOOKUP(1,0/(项目收支汇总表!A5:A306="2.11.1"),项目收支汇总表!C5:C306) -> 0 | CB7: =LOOKUP(1,0/(项目收支汇总表!A5:A306="2.15"),项目收支汇总表!C5:C306) -> 0 | CC7: =BX7+BY7+BZ7+CA7+CB7 -> 0 | CD7: =LOOKUP(1,0/(项目收支汇总表!A5:A306="2.12.1"),项目收支汇总表!C5:C306) -> 0 | CE7: =LOOKUP(1,0/(项目收支汇总表!A5:A306="2.12.3"),项目收支汇总表!C5:C306) -> 0 | CF7: =LOOKUP(1,0/(项目收支汇总表!A5:A306="2.13.1"),项目收支汇总表!C5:C306) -> 0 | CG7: =CD7+CE7+CF7 -> 0 | CH7: =LOOKUP(1,0/(项目收支汇总表!A5:A306="2.14"),项目收支汇总表!C5:C306) -> 0 | CI7: =CU7+CZ7+DD7+DE7 -> 0 | CJ7: ='项目月度完全成本、付款明细表-表3.2'!X8 -> 0 | CK7: ='项目月度完全成本、付款明细表-表3.2'!X11 -> 0 | CL7: ='项目月度完全成本、付款明细表-表3.2'!X14 -> 0 | CM7: ='项目月度完全成本、付款明细表-表3.2'!X17 -> 0 | CN7: ='项目月度完全成本、付款明细表-表3.2'!X20 -> 0 | CO7: ='项目月度完全成本、付款明细表-表3.2'!X23 -> 0 | CP7: ='项目月度完全成本、付款明细表-表3.2'!X26 -> 0 | CQ7: ='项目月度完全成本、付款明细表-表3.2'!X30 -> 0 | CR7: ='项目月度完全成本、付款明细表-表3.2'!X57 -> 0 | CS7: ='项目月度完全成本、付款明细表-表3.2'!X61 -> 0 | CT7: ='项目月度完全成本、付款明细表-表3.2'!X66 -> 0 | CU7: =CJ7+CK7+CL7+CM7+CN7+CO7+CP7+CQ7+CR7+CS7+CT7 -> 0 | CV7: ='项目月度完全成本、付款明细表-表3.2'!X72 -> 0 | CW7: ='项目月度完全成本、付款明细表-表3.2'!$X73 -> 0 | CX7: ='项目月度完全成本、付款明细表-表3.2'!$X74 -> 0 | CY7: ='项目月度完全成本、付款明细表-表3.2'!$X75 -> 0 | CZ7: =CV7+CW7+CX7+CY7 -> 0 | DA7: ='项目月度完全成本、付款明细表-表3.2'!$X77 -> 0 | DB7: ='项目月度完全成本、付款明细表-表3.2'!$X78 -> 0 | DC7: ='项目月度完全成本、付款明细表-表3.2'!$X79 -> 0 | DD7: =DA7+DB7+DC7 -> 0 | DE7: ='项目月度完全成本、付款明细表-表3.2'!X80 -> 0 | DF7: =BM7-CI7 -> 0 | DG7: =BU7+CG7+CH7-CU7-DD7-DE7 -> 0 | DH7: ='项目月度业主产值表-表3.1'!R6 -> 0 | DI7: ='项目月度业主产值表-表3.1'!S6 -> 0 | DJ7: =DH7+DI7 -> 0 | DK7: ='项目月度完全成本、付款明细表-表3.2'!AG69 -> 0 | DL7: ='项目月度完全成本、付款明细表-表3.2'!AG70 -> 0 | DM7: =DK7+DL7 -> 0 | DN7: ='项目月度完全成本、付款明细表-表3.2'!AI69 -> 0 | DO7: ='项目月度完全成本、付款明细表-表3.2'!AI70 -> 0 | DP7: =DN7+DO7 -> 0 | DQ7: =IF(DP7>0,DF7+DJ7-DP7,DF7+DJ7-DM7) -> 0 | DR7: =IF(DN7>0,DG7+DH7-DN7,DG7+DH7-DK7) -> 0

Sheet 项目月度业主产值表-表3.1
A1: 表3.1 - 项目月度业主产值表
A2: 项目名称: | F2: 报告期间: | U2: 单位: 元
A3: 序号 | B3: 日 期 | C3: 本期产值核定期间 | D3: 开工至上年度产值 | G3: 本年度累计实际完成产值 | J3: 其中:本月实际完成产值 | M3: 自开工累计实际完成产值 | P3: 二、应收款（合约） （不考虑付款周期） | R3: 资金收款计划 | U3: 备 注
D4: 业主已确认 | E4: 业主待确认 | F4: 合计 | G4: 业主已确认 | H4: 业主待确认 | I4: 合计 | J4: 业主已确认 | K4: 业主待确认 | L4: 合计 | M4: 业主已确认 | N4: 业主待确认 | O4: 合计 | P4: 应收款计算结果 | Q4: 详细计算式（以下示例) | R4: 业主收款 | S4: 往来收入 | T4: 小计
B5: 计算编号 | D5: 1.1 | E5: 1.2 | F5: 1.3=1.1+1.2 | G5: 1.4=1.10-1.1 | H5: 1.5=1.11-1.2 | I5: 1.6=1.4+1.5 | J5: 1.7 | K5: 1.8 | L5: 1.9=1.7+1.8 | M5: 1.10 | N5: 1.11 | O5: 1.13=1.10+1.11 | P5: 2.1 | Q5: 2.2 | R5: 3.1 | S5: 3.2 | T5: 3.3=3.1+3.2
A6: 1 | F6: =D6+E6 -> 0 | G6: =M6-D6 -> 0 | H6: =N6-E6 -> 0 | I6: =G6+H6 -> 0 | L6: =J6+K6 -> 0 | N6: ='项目月度业主待确产值分析表-表3.1.1'!C8 -> 0 | O6: =M6+N6 -> 0 | Q6: 50[安全文明施工费预付款]+100[业主审核产值]*70%[合同约定付款比例]-20[预、其他扣款] | T6: =R6+S6 -> 0
A7: 填表说明：本表用于按合同约定应收款额计算，要求有详细的计算过程及说明。产值单扫描必须清晰可见 附件：业主确实产值单扫描件，若是结算金额时，可扫描盖章或签字的能反映金额的结算封面即可。

Sheet 项目月度业主待确产值分析表-表3.1.1
A1: 表3.1.1 项目月度业主待确产值分析表
A2: 项目名称: | D2: 报告期间:
A3: 序号 | B3: 项目名称 | C3: 主要内容 | D3: 主要内容 | E3: 备注
A5: 1 | B5: ="[10]实际形象进度描述" -> [10]实际形象进度描述
A6: 2 | B6: ="[20]合同付款摘要" -> [20]合同付款摘要
A7: 3 | B7: ="[30]待确主要原因描述" -> [30]待确主要原因描述
A8: 4 | B8: ="[40]待确金额" -> [40]待确金额 | E8: 须提供与金额相对应的量、价计算文件作为附件支撑，否则对金额不认可

Sheet 项目月度完全成本、付款明细表-表3.2
A1: 表3.2 - 项目月度完全成本、付款明细表
A2: 项目名称: | H2: 报告期间: | K2: 建筑面积: | O2: 管理费率: | P2: =LOOKUP(1,0/(项目收支汇总表!A5:A306="5.1"),项目收支汇总表!C5:C306) -> 0.03
A3: 序号 | B3: 成本项目 | C3: 代码 | D3: 成本属性 | E3: 级数 | F3: 基本信息 | N3: 自开工累计已发生成本 （完全成本） | Q3: 合计 | R3: 其中：本月已发生成本（完全成本） | U3: 成本刚性度 (%) | V3: 应付款 | W3: 应付款 | X3: 开累已付款 | Z3: 应付未付款 （合约） | AA3: 应付未付款 （合约） | AB3: 应付未付款 （100%） | AE3: 资金计划 | AK3: 上月资金计划执行情况 | AM3: 质保金 | AP3: 备 注 | AQ3: 合同id
F4: 合同编码 | G4: 合同名称 | H4: 合同内容 | I4: 分/供商名称 | J4: 合同总金额 | K4: 付款比例 | L4: 税率 （%） | M4: 是否办理结算 | N4: 已确认 | O4: 待确认 | P4: 合计 | Q4: 其中:人工费 | R4: 已确认 | S4: 待确认 | T4: 合计 | V4: 开累已确应付款 （合约） | W4: 其中:人工费 （100%） | X4: 金额 | Y4: 比例 | Z4: 开累应付未付款 （合约） | AA4: 其中:人工费 （100%） | AB4: 应付未付款 （不含待确成本） | AC4: 应付未付款 （待确成本） | AD4: 小计 | AE4: 付款方式 | AF4: 付款类型 | AG4: 项目支出计划 | AH4: 累计付款比例（含本次） | AI4: 公司批准金额 | AJ4: 批准累计付款比例 | AK4: 上月审批数 | AL4: 上月执行数 | AM4: 是否有质保金 | AN4: 质保金金额 | AO4: 质保金到期时间
B5: 计算编号 | N5: 1.1 | O5: 1.2 | P5: 1.3=1.1+1.2 | Q5: 1.3.1 | R5: 1.4 | S5: 1.5 | T5: 1.6=1.4+1.5 | U5: 1.7=1.1/1.3 | V5: 2.1 | W5: 2.2 | X5: 3.1 | Y5: 3.2=3.1/1.1 | Z5: 4.1=2.1-3.1 | AA5: 4.2=2.2-3.1 | AB5: 5.1=1.1-3.1 | AC5: 5.2=1.2 | AD5: 5.3=5.1+5.2 | AE5: 6.1 | AF5: 6.2 | AG5: 6.3 | AH5: 6.4=（3.1+6.3）/1.1 | AI5: 6.5 | AJ5: 6.6=（3.1+6.5）/1.1 | AK5: 7.1 | AL5: 7.2 | AM5: 8.1 | AN5: 8.2 | AO5: 8.3
A7: 一 | B7: 直接成本 | C7: 540101 | E7: 1 | J7: =J8+J11+J14+J17+J20+J23+J26 -> 0 | N7: =N8+N11+N14+N17+N20+N23+N26 -> 0 | O7: =O8+O11+O14+O17+O20+O23+O26 -> 0 | P7: =N7+O7 -> 0 | Q7: =Q8+Q11+Q14+Q17+Q20+Q23+Q26 -> 0 | R7: =R8+R11+R14+R17+R20+R23+R26 -> 0 | S7: =S8+S11+S14+S17+S20+S23+S26 -> 0 | T7: =R7+S7 -> 0 | U7: =N7/P7 -> #DIV/0! | V7: =V8+V11+V14+V17+V20+V23+V26 -> 0 | W7: =W8+W11+W14+W17+W20+W23+W26 -> 0 | X7: =X8+X11+X14+X17+X20+X23+X26 -> 0 | Y7: =X7/N7 -> #DIV/0! | Z7: =V7-X7 -> 0 | AA7: =AA8+AA11+AA14+AA17+AA20+AA23+AA26 -> 0 | AB7: =AB8+AB11+AB14+AB17+AB20+AB23+AB26 -> 0 | AC7: =AC8+AC11+AC14+AC17+AC20+AC23+AC26 -> 0 | AD7: =AB7+AC7 -> 0 | AG7: =AG8+AG11+AG14+AG17+AG20+AG23+AG26 -> 0 | AH7: =(X7+AG7)/N7 -> #DIV/0! | AI7: =AI8+AI11+AI14+AI17+AI20+AI23+AI26 -> 0 | AJ7: =(X7+AI7)/N7 -> #DIV/0! | AK7: =AK8+AK11+AK14+AK17+AK20+AK23+AK26 -> 0 | AL7: =AL8+AL11+AL14+AL17+AL20+AL23+AL26 -> 0 | AN7: =AN8+AN11+AN14+AN17+AN20+AN23+AN26 -> 0
A8: 1 | B8: 劳务分包 | C8: 54010101 | D8: 劳务 | E8: 2 | J8: =SUMIF($C9:$C10,$C8&":*",J9:J10) -> 0 | N8: =SUMIF($C9:$C10,$C8&":*",N9:N10) -> 0 | O8: =SUMIF($C9:$C10,$C8&":*",O9:O10) -> 0 | P8: =N8+O8 -> 0 | Q8: =SUMIF($C9:$C10,$C8&":*",Q9:Q10) -> 0 | R8: =SUMIF($C9:$C10,$C8&":*",R9:R10) -> 0 | S8: =SUMIF($C9:$C10,$C8&":*",S9:S10) -> 0 | T8: =R8+S8 -> 0 | U8: =N8/P8 -> #DIV/0! | V8: =SUMIF($C9:$C10,$C8&":*",V9:V10) -> 0 | W8: =SUMIF($C9:$C10,$C8&":*",W9:W10) -> 0 | X8: =SUMIF($C9:$C10,$C8&":*",X9:X10) -> 0 | Y8: =X8/N8 -> #DIV/0! | Z8: =V8-X8 -> 0 | AA8: =SUMIF($C9:$C10,$C8&":*",AA9:AA10) -> 0 | AB8: =SUM(AB9:AB10) -> 0 | AC8: =O8 -> 0 | AD8: =AB8+AC8 -> 0 | AG8: =SUMIF($C9:$C10,$C8&":*",AG9:AG10) -> 0 | AH8: =(X8+AG8)/N8 -> #DIV/0! | AI8: =SUMIF($C9:$C10,$C8&":*",AI9:AI10) -> 0 | AJ8: =(X8+AI8)/N8 -> #DIV/0! | AK8: =SUMIF($C9:$C10,$C8&":*",AK9:AK10) -> 0 | AL8: =SUMIF($C9:$C10,$C8&":*",AL9:AL10) -> 0 | AN8: =SUMIF($C9:$C10,$C8&":*",AN9:AN10) -> 0
A9: 1.0 | B9: 模板行 | C9: 54010101:1 | D9: 劳务 | E9: 3 | P9: =N9+O9 -> 0 | T9: =R9+S9 -> 0 | U9: =N9/P9 -> #DIV/0! | V9: =N9*K9 -> 0 | Y9: =X9/N9 -> #DIV/0! | Z9: =V9-X9 -> 0 | AA9: =IF(W9-X9>0,W9-X9,0) -> 0 | AB9: =IF(G9="内部调拨",0,N9-X9) -> 0 | AC9: =O9 -> 0 | AD9: =AB9+AC9 -> 0 | AH9: =(X9+AG9)/N9 -> #DIV/0! | AJ9: =(X9+AI9)/N9 -> #DIV/0!
A10: 1.999 | B10: 模板行 | C10: 54010101:1 | D10: 劳务 | E10: 3 | P10: =N10+O10 -> 0 | T10: =R10+S10 -> 0 | U10: =N10/P10 -> #DIV/0! | V10: =N10*K10 -> 0 | Y10: =X10/N10 -> #DIV/0! | Z10: =V10-X10 -> 0 | AA10: =IF(W10-X10>0,W10-X10,0) -> 0 | AB10: =IF(G10="内部调拨",0,N10-X10) -> 0 | AC10: =O10 -> 0 | AD10: =AB10+AC10 -> 0 | AH10: =(X10+AG10)/N10 -> #DIV/0! | AJ10: =(X10+AI10)/N10 -> #DIV/0!
A11: 2 | B11: 专业分包 | C11: 54010102 | D11: 专业分包 | E11: 2 | J11: =SUMIF($C12:$C13,$C11&":*",J12:J13) -> 0 | N11: =SUMIF($C12:$C13,$C11&":*",N12:N13) -> 0 | O11: =SUMIF($C12:$C13,$C11&":*",O12:O13) -> 0 | P11: =N11+O11 -> 0 | Q11: =SUMIF($C12:$C13,$C11&":*",Q12:Q13) -> 0 | R11: =SUMIF($C12:$C13,$C11&":*",R12:R13) -> 0 | S11: =SUMIF($C12:$C13,$C11&":*",S12:S13) -> 0 | T11: =R11+S11 -> 0 | U11: =N11/P11 -> #DIV/0! | V11: =SUMIF($C12:$C13,$C11&":*",V12:V13) -> 0 | W11: =SUMIF($C12:$C13,$C11&":*",W12:W13) -> 0 | X11: =SUMIF($C12:$C13,$C11&":*",X12:X13) -> 0 | Y11: =X11/N11 -> #DIV/0! | Z11: =V11-X11 -> 0 | AA11: =SUMIF($C12:$C13,$C11&":*",AA12:AA13) -> 0 | AB11: =SUM(AB12:AB13) -> 0 | AC11: =O11 -> 0 | AD11: =AB11+AC11 -> 0 | AG11: =SUMIF($C12:$C13,$C11&":*",AG12:AG13) -> 0 | AH11: =(X11+AG11)/N11 -> #DIV/0! | AI11: =SUMIF($C12:$C13,$C11&":*",AI12:AI13) -> 0 | AJ11: =(X11+AI11)/N11 -> #DIV/0! | AK11: =SUMIF($C12:$C13,$C11&":*",AK12:AK13) -> 0 | AL11: =SUMIF($C12:$C13,$C11&":*",AL12:AL13) -> 0 | AN11: =SUMIF($C12:$C13,$C11&":*",AN12:AN13) -> 0
A12: 2.0 | B12: 模板行 | C12: 54010102:1 | D12: 专业分包 | E12: 3 | P12: =N12+O12 -> 0 | T12: =R12+S12 -> 0 | U12: =N12/P12 -> #DIV/0! | V12: =N12*K12 -> 0 | Y12: =X12/N12 -> #DIV/0! | Z12: =V12-X12 -> 0 | AA12: =IF(W12-X12>0,W12-X12,0) -> 0 | AB12: =IF(G12="内部调拨",0,N12-X12) -> 0 | AC12: =O12 -> 0 | AD12: =AB12+AC12 -> 0 | AH12: =(X12+AG12)/N12 -> #DIV/0! | AJ12: =(X12+AI12)/N12 -> #DIV/0!
A13: 2.999 | B13: 模板行 | C13: 54010102:1 | D13: 专业分包 | E13: 3 | P13: =N13+O13 -> 0 | T13: =R13+S13 -> 0 | U13: =N13/P13 -> #DIV/0! | V13: =N13*K13 -> 0 | Y13: =X13/N13 -> #DIV/0! | Z13: =V13-X13 -> 0 | AA13: =IF(W13-X13>0,W13-X13,0) -> 0 | AB13: =IF(G13="内部调拨",0,N13-X13) -> 0 | AC13: =O13 -> 0 | AD13: =AB13+AC13 -> 0 | AH13: =(X13+AG13)/N13 -> #DIV/0! | AJ13: =(X13+AI13)/N13 -> #DIV/0!
A14: 3 | B14: 材料、设备 | C14: 54010103 | D14: 材料、设备 | E14: 2 | J14: =SUMIF($C15:$C16,$C14&":*",J15:J16) -> 0 | N14: =SUMIF($C15:$C16,$C14&":*",N15:N16) -> 0 | O14: =SUMIF($C15:$C16,$C14&":*",O15:O16) -> 0 | P14: =N14+O14 -> 0 | Q14: =SUMIF($C15:$C16,$C14&":*",Q15:Q16) -> 0 | R14: =SUMIF($C15:$C16,$C14&":*",R15:R16) -> 0 | S14: =SUMIF($C15:$C16,$C14&":*",S15:S16) -> 0 | T14: =R14+S14 -> 0 | U14: =N14/P14 -> #DIV/0! | V14: =SUMIF($C15:$C16,$C14&":*",V15:V16) -> 0 | W14: =SUMIF($C15:$C16,$C14&":*",W15:W16) -> 0 | X14: =SUMIF($C15:$C16,$C14&":*",X15:X16) -> 0 | Y14: =X14/N14 -> #DIV/0! | Z14: =V14-X14 -> 0 | AA14: =SUMIF($C15:$C16,$C14&":*",AA15:AA16) -> 0 | AB14: =SUM(AB15:AB16) -> 0 | AC14: =O14 -> 0 | AD14: =AB14+AC14 -> 0 | AG14: =SUMIF($C15:$C16,$C14&":*",AG15:AG16) -> 0 | AH14: =(X14+AG14)/N14 -> #DIV/0! | AI14: =SUMIF($C15:$C16,$C14&":*",AI15:AI16) -> 0 | AJ14: =(X14+AI14)/N14 -> #DIV/0! | AK14: =SUMIF($C15:$C16,$C14&":*",AK15:AK16) -> 0 | AL14: =SUMIF($C15:$C16,$C14&":*",AL15:AL16) -> 0 | AN14: =SUMIF($C15:$C16,$C14&":*",AN15:AN16) -> 0
A15: 3.0 | B15: 模板行 | C15: 54010103:1 | D15: 材料、设备 | E15: 3 | P15: =N15+O15 -> 0 | T15: =R15+S15 -> 0 | U15: =N15/P15 -> #DIV/0! | V15: =N15*K15 -> 0 | Y15: =X15/N15 -> #DIV/0! | Z15: =V15-X15 -> 0 | AA15: =IF(W15-X15>0,W15-X15,0) -> 0 | AB15: =IF(G15="内部调拨",0,N15-X15) -> 0 | AC15: =IF(G15="内部调拨",0,O15) -> 0 | AD15: =AB15+AC15 -> 0 | AH15: =(X15+AG15)/N15 -> #DIV/0! | AJ15: =(X15+AI15)/N15 -> #DIV/0!
A16: 3.999 | B16: 模板行 | C16: 54010103:1 | D16: 材料、设备 | E16: 3 | M16: 否 | P16: =N16+O16 -> 0 | T16: =R16+S16 -> 0 | U16: =N16/P16 -> #DIV/0! | V16: =N16*K16 -> 0 | Y16: =X16/N16 -> #DIV/0! | Z16: =V16-X16 -> 0 | AA16: =IF(W16-X16>0,W16-X16,0) -> 0 | AB16: =IF(G16="内部调拨",0,N16-X16) -> 0 | AC16: =IF(G16="内部调拨",0,O16) -> 0 | AD16: =AB16+AC16 -> 0 | AH16: =(X16+AG16)/N16 -> #DIV/0! | AJ16: =(X16+AI16)/N16 -> #DIV/0!
A17: 4 | B17: 机械设备租赁 | C17: 54010104 | D17: 机械设备租赁 | E17: 2 | J17: =SUMIF($C18:$C19,$C17&":*",J18:J19) -> 0 | N17: =SUMIF($C18:$C19,$C17&":*",N18:N19) -> 0 | O17: =SUMIF($C18:$C19,$C17&":*",O18:O19) -> 0 | P17: =N17+O17 -> 0 | Q17: =SUMIF($C18:$C19,$C17&":*",Q18:Q19) -> 0 | R17: =SUMIF($C18:$C19,$C17&":*",R18:R19) -> 0 | S17: =SUMIF($C18:$C19,$C17&":*",S18:S19) -> 0 | T17: =R17+S17 -> 0 | U17: =N17/P17 -> #DIV/0! | V17: =SUMIF($C18:$C19,$C17&":*",V18:V19) -> 0 | W17: =SUMIF($C18:$C19,$C17&":*",W18:W19) -> 0 | X17: =SUMIF($C18:$C19,$C17&":*",X18:X19) -> 0 | Y17: =X17/N17 -> #DIV/0! | Z17: =V17-X17 -> 0 | AA17: =SUMIF($C18:$C19,$C17&":*",AA18:AA19) -> 0 | AB17: =SUM(AB18:AB19) -> 0 | AC17: =O17 -> 0 | AD17: =AB17+AC17 -> 0 | AG17: =SUMIF($C18:$C19,$C17&":*",AG18:AG19) -> 0 | AH17: =(X17+AG17)/N17 -> #DIV/0! | AI17: =SUMIF($C18:$C19,$C17&":*",AI18:AI19) -> 0 | AJ17: =(X17+AI17)/N17 -> #DIV/0! | AK17: =SUMIF($C18:$C19,$C17&":*",AK18:AK19) -> 0 | AL17: =SUMIF($C18:$C19,$C17&":*",AL18:AL19) -> 0 | AN17: =SUMIF($C18:$C19,$C17&":*",AN18:AN19) -> 0
A18: 4.0 | B18: 模板行 | C18: 54010104:1 | D18: 机械设备租赁 | E18: 3 | P18: =N18+O18 -> 0 | T18: =R18+S18 -> 0 | U18: =N18/P18 -> #DIV/0! | V18: =N18*K18 -> 0 | Y18: =X18/N18 -> #DIV/0! | Z18: =V18-X18 -> 0 | AA18: =IF(W18-X18>0,W18-X18,0) -> 0 | AB18: =IF(G18="内部调拨",0,N18-X18) -> 0 | AC18: =O18 -> 0 | AD18: =AB18+AC18 -> 0 | AH18: =(X18+AG18)/N18 -> #DIV/0! | AJ18: =(X18+AI18)/N18 -> #DIV/0!
A19: 4.999 | B19: 模板行 | C19: 54010104:1 | D19: 机械设备租赁 | E19: 3 | P19: =N19+O19 -> 0 | T19: =R19+S19 -> 0 | U19: =N19/P19 -> #DIV/0! | V19: =N19*K19 -> 0 | Y19: =X19/N19 -> #DIV/0! | Z19: =V19-X19 -> 0 | AA19: =IF(W19-X19>0,W19-X19,0) -> 0 | AB19: =IF(G19="内部调拨",0,N19-X19) -> 0 | AC19: =O19 -> 0 | AD19: =AB19+AC19 -> 0 | AH19: =(X19+AG19)/N19 -> #DIV/0! | AJ19: =(X19+AI19)/N19 -> #DIV/0!
A20: 5 | B20: 周转材料租赁 | C20: 54010105 | D20: 周转材料租赁 | E20: 2 | J20: =SUMIF($C21:$C22,$C20&":*",J21:J22) -> 0 | N20: =SUMIF($C21:$C22,$C20&":*",N21:N22) -> 0 | O20: =SUMIF($C21:$C22,$C20&":*",O21:O22) -> 0 | P20: =N20+O20 -> 0 | Q20: =SUMIF($C21:$C22,$C20&":*",Q21:Q22) -> 0 | R20: =SUMIF($C21:$C22,$C20&":*",R21:R22) -> 0 | S20: =SUMIF($C21:$C22,$C20&":*",S21:S22) -> 0 | T20: =R20+S20 -> 0 | U20: =N20/P20 -> #DIV/0! | V20: =SUMIF($C21:$C22,$C20&":*",V21:V22) -> 0 | W20: =SUMIF($C21:$C22,$C20&":*",W21:W22) -> 0 | X20: =SUMIF($C21:$C22,$C20&":*",X21:X22) -> 0 | Y20: =X20/N20 -> #DIV/0! | Z20: =V20-X20 -> 0 | AA20: =SUMIF($C21:$C22,$C20&":*",AA21:AA22) -> 0 | AB20: =SUM(AB21:AB22) -> 0 | AC20: =O20 -> 0 | AD20: =AB20+AC20 -> 0 | AG20: =SUMIF($C21:$C22,$C20&":*",AG21:AG22) -> 0 | AH20: =(X20+AG20)/N20 -> #DIV/0! | AI20: =SUMIF($C21:$C22,$C20&":*",AI21:AI22) -> 0 | AJ20: =(X20+AI20)/N20 -> #DIV/0! | AK20: =SUMIF($C21:$C22,$C20&":*",AK21:AK22) -> 0 | AL20: =SUMIF($C21:$C22,$C20&":*",AL21:AL22) -> 0 | AN20: =SUMIF($C21:$C22,$C20&":*",AN21:AN22) -> 0
A21: 5.0 | B21: 模板行 | C21: 54010105:1 | D21: 周转材料租赁 | E21: 3 | P21: =N21+O21 -> 0 | T21: =R21+S21 -> 0 | U21: =N21/P21 -> #DIV/0! | V21: =N21*K21 -> 0 | Y21: =X21/N21 -> #DIV/0! | Z21: =V21-X21 -> 0 | AA21: =IF(W21-X21>0,W21-X21,0) -> 0 | AB21: =IF(G21="内部调拨",0,N21-X21) -> 0 | AC21: =O21 -> 0 | AD21: =AB21+AC21 -> 0 | AH21: =(X21+AG21)/N21 -> #DIV/0! | AJ21: =(X21+AI21)/N21 -> #DIV/0!
A22: 5.999 | B22: 模板行 | C22: 54010105:1 | D22: 周转材料租赁 | E22: 3 | P22: =N22+O22 -> 0 | T22: =R22+S22 -> 0 | U22: =N22/P22 -> #DIV/0! | V22: =N22*K22 -> 0 | Y22: =X22/N22 -> #DIV/0! | Z22: =V22-X22 -> 0 | AA22: =IF(W22-X22>0,W22-X22,0) -> 0 | AB22: =IF(G22="内部调拨",0,N22-X22) -> 0 | AC22: =O22 -> 0 | AD22: =AB22+AC22 -> 0 | AH22: =(X22+AG22)/N22 -> #DIV/0! | AJ22: =(X22+AI22)/N22 -> #DIV/0!
A23: 6 | B23: 安全文明施工费 | C23: 54010106 | D23: 安全文明施工 | E23: 2 | J23: =SUMIF($C24:$C25,$C23&":*",J24:J25) -> 0 | N23: =SUMIF($C24:$C25,$C23&":*",N24:N25) -> 0 | O23: =SUMIF($C24:$C25,$C23&":*",O24:O25) -> 0 | P23: =N23+O23 -> 0 | Q23: =SUMIF($C24:$C25,$C23&":*",Q24:Q25) -> 0 | R23: =SUMIF($C24:$C25,$C23&":*",R24:R25) -> 0 | S23: =SUMIF($C24:$C25,$C23&":*",S24:S25) -> 0 | T23: =R23+S23 -> 0 | U23: =N23/P23 -> #DIV/0! | V23: =SUMIF($C24:$C25,$C23&":*",V24:V25) -> 0 | W23: =SUMIF($C24:$C25,$C23&":*",W24:W25) -> 0 | X23: =SUMIF($C24:$C25,$C23&":*",X24:X25) -> 0 | Y23: =X23/N23 -> #DIV/0! | Z23: =V23-X23 -> 0 | AA23: =SUMIF($C24:$C25,$C23&":*",AA24:AA25) -> 0 | AB23: =SUM(AB24:AB25) -> 0 | AC23: =O23 -> 0 | AD23: =AB23+AC23 -> 0 | AG23: =SUMIF($C24:$C25,$C23&":*",AG24:AG25) -> 0 | AH23: =(X23+AG23)/N23 -> #DIV/0! | AI23: =SUMIF($C24:$C25,$C23&":*",AI24:AI25) -> 0 | AJ23: =(X23+AI23)/N23 -> #DIV/0! | AK23: =SUMIF($C24:$C25,$C23&":*",AK24:AK25) -> 0 | AL23: =SUMIF($C24:$C25,$C23&":*",AL24:AL25) -> 0 | AN23: =SUMIF($C24:$C25,$C23&":*",AN24:AN25) -> 0
A24: 6.0 | B24: 模板行 | C24: 54010106:1 | D24: 安全文明施工 | E24: 3 | P24: =N24+O24 -> 0 | T24: =R24+S24 -> 0 | U24: =N24/P24 -> #DIV/0! | V24: =N24*K24 -> 0 | Y24: =X24/N24 -> #DIV/0! | Z24: =V24-X24 -> 0 | AA24: =IF(W24-X24>0,W24-X24,0) -> 0 | AB24: =IF(G24="内部调拨",0,N24-X24) -> 0 | AC24: =O24 -> 0 | AD24: =AB24+AC24 -> 0 | AH24: =(X24+AG24)/N24 -> #DIV/0! | AJ24: =(X24+AI24)/N24 -> #DIV/0!
A25: 6.999 | B25: 模板行 | C25: 54010106:1 | D25: 安全文明施工 | E25: 3 | P25: =N25+O25 -> 0 | T25: =R25+S25 -> 0 | U25: =N25/P25 -> #DIV/0! | V25: =N25*K25 -> 0 | Y25: =X25/N25 -> #DIV/0! | Z25: =V25-X25 -> 0 | AA25: =IF(W25-X25>0,W25-X25,0) -> 0 | AB25: =IF(G25="内部调拨",0,N25-X25) -> 0 | AC25: =O25 -> 0 | AD25: =AB25+AC25 -> 0 | AH25: =(X25+AG25)/N25 -> #DIV/0! | AJ25: =(X25+AI25)/N25 -> #DIV/0!
A26: 7 | B26: 其他直接费 | C26: 54010107 | D26: 其他直接费 | E26: 2 | J26: =SUMIF($C27:$C29,$C26&":*",J27:J29) -> 0 | N26: =SUMIF($C27:$C29,$C26&":*",N27:N29) -> 0 | O26: =SUMIF($C27:$C29,$C26&":*",O27:O29) -> 0 | P26: =N26+O26 -> 0 | Q26: =SUMIF($C27:$C29,$C26&":*",Q27:Q29) -> 0 | R26: =SUMIF($C27:$C29,$C26&":*",R27:R29) -> 0 | S26: =SUMIF($C27:$C29,$C26&":*",S27:S29) -> 0 | T26: =R26+S26 -> 0 | U26: =N26/P26 -> #DIV/0! | V26: =SUMIF($C27:$C29,$C26&":*",V27:V29) -> 0 | W26: =SUMIF($C27:$C29,$C26&":*",W27:W29) -> 0 | X26: =SUMIF($C27:$C29,$C26&":*",X27:X29) -> 0 | Y26: =X26/N26 -> #DIV/0! | Z26: =V26-X26 -> 0 | AA26: =SUMIF($C27:$C29,$C26&":*",AA27:AA29) -> 0 | AB26: =SUM(AB27:AB29) -> 0 | AC26: =O26 -> 0 | AD26: =AB26+AC26 -> 0 | AG26: =SUMIF($C27:$C29,$C26&":*",AG27:AG29) -> 0 | AH26: =(X26+AG26)/N26 -> #DIV/0! | AI26: =SUMIF($C27:$C29,$C26&":*",AI27:AI29) -> 0 | AJ26: =(X26+AI26)/N26 -> #DIV/0! | AK26: =SUMIF($C27:$C29,$C26&":*",AK27:AK29) -> 0 | AL26: =SUMIF($C27:$C29,$C26&":*",AL27:AL29) -> 0 | AN26: =SUMIF($C27:$C29,$C26&":*",AN27:AN29) -> 0
A27: 7.0 | B27: 模板行 | C27: 54010107:1 | D27: 其他直接费 | E27: 3 | P27: =N27+O27 -> 0 | T27: =R27+S27 -> 0 | U27: =N27/P27 -> #DIV/0! | V27: =N27*K27 -> 0 | Y27: =X27/N27 -> #DIV/0! | Z27: =V27-X27 -> 0 | AA27: =IF(W27-X27>0,W27-X27,0) -> 0 | AB27: =IF(G27="内部调拨",0,N27-X27) -> 0 | AC27: =O27 -> 0 | AD27: =AB27+AC27 -> 0 | AH27: =(X27+AG27)/N27 -> #DIV/0! | AJ27: =(X27+AI27)/N27 -> #DIV/0!
A28: 7.1 | B28: 其它直接费(报销) | C28: 54010107:1 | D28: 其他直接费 | E28: 3 | F28: ZX_WHT_7_BX | G28: 其它直接费(报销) | N28: =X28 -> 0 | P28: =N28+O28 -> 0 | T28: =R28+S28 -> 0 | U28: =N28/P28 -> #DIV/0! | V28: =X28 -> 0 | X28: =LOOKUP(1,0/(项目收支汇总表!A5:A306="4.2.2"),项目收支汇总表!C5:C306)-LOOKUP(1,0/(项目收支汇总表!A5:A306="4.2.2.4"),项目收支汇总表!C5:C306) -> 0 | Y28: =X28/N28 -> #DIV/0! | Z28: =V28-X28 -> 0 | AA28: =IF(W28-X28>0,W28-X28,0) -> 0 | AB28: =N28-X28 -> 0 | AC28: =O28 -> 0 | AD28: =AB28+AC28 -> 0 | AH28: =(X28+AG28)/N28 -> #DIV/0! | AJ28: =(X28+AI28)/N28 -> #DIV/0!
A29: 7.999 | B29: 模板行 | C29: 54010107:1 | D29: 其他直接费 | E29: 3 | P29: =N29+O29 -> 0 | T29: =R29+S29 -> 0 | U29: =N29/P29 -> #DIV/0! | V29: =J29*K29 -> 0 | Y29: =X29/N29 -> #DIV/0! | Z29: =V29-X29 -> 0 | AA29: =IF(W29-X29>0,W29-X29,0) -> 0 | AB29: =IF(G29="内部调拨",0,N29-X29) -> 0 | AC29: =O29 -> 0 | AD29: =AB29+AC29 -> 0 | AH29: =(X29+AG29)/N29 -> #DIV/0! | AJ29: =(X29+AI29)/N29 -> #DIV/0!
A30: 二 | B30: 间接成本 | C30: 540102 | D30: 间接费 | E30: 1 | N30: =N31+N34+N53+N54+N55+N56 -> 0 | O30: =O31+O34+O53+O54+O55+O56 -> 0 | P30: =P31+P34+P53+P54+P55+P56 -> 0 | Q30: =Q31+Q34+Q53+Q54+Q55+Q56 -> 0 | R30: =R31+R34+R53+R54+R55+R56 -> 0 | S30: =S31+S34+S53+S54+S55+S56 -> 0 | T30: =T31+T34+T53+T54+T55+T56 -> 0 | U30: =N30/P30 -> #DIV/0! | V30: =V31+V34+V53+V54+V55+V56 -> 0 | W30: =W31+W34+W53+W54+W55+W56 -> 0 | X30: =X31+X34+X53+X54+X55+X56 -> 0 | Y30: =X30/N30 -> #DIV/0! | Z30: =V30-X30 -> 0 | AA30: =AA31+AA34+AA53+AA54+AA55+AA56 -> 0 | AB30: =N30-X30 -> 0 | AC30: =O30 -> 0 | AD30: =AB30+AC30 -> 0 | AG30: =AG31+AG34+AG53+AG54+AG55+AG56 -> 0 | AH30: =(X30+AG30)/N30 -> #DIV/0! | AI30: =AI31+AI34+AI53+AI54+AI55+AI56 -> 0 | AJ30: =(X30+AI30)/N30 -> #DIV/0! | AK30: =AK31+AK34+AK53+AK54+AK55+AK56 -> 0 | AL30: =AL31+AL34+AL53+AL54+AL55+AL56 -> 0
A31: 2.1 | B31: 工资及福利费测算 | C31: 54010201 | D31: 间接费 | E31: 2 | N31: =N32+N33 -> 0 | O31: =O32+O33 -> 0 | P31: =N31+O31 -> 0 | Q31: =Q32+Q33 -> 0 | R31: =R32+R33 -> 0 | S31: =S32+S33 -> 0 | T31: =R31+S31 -> 0 | U31: =N31/P31 -> #DIV/0! | V31: =V32+V33 -> 0 | W31: =W32+W33 -> 0 | X31: =X32+X33 -> 0 | Y31: =X31/N31 -> #DIV/0! | Z31: =V31-X31 -> 0 | AA31: =AA32+AA33 -> 0 | AB31: =N31-X31 -> 0 | AC31: =O31 -> 0 | AD31: =AB31+AC31 -> 0 | AG31: =AG32+AG33 -> 0 | AH31: =(X31+AG31)/N31 -> #DIV/0! | AI31: =AI32+AI33 -> 0 | AJ31: =(X31+AI31)/N31 -> #DIV/0! | AK31: =AK32+AK33 -> 0 | AL31: =AL32+AL33 -> 0
A32: 2.1.1 | B32: 工资及福利费（入职） | C32: 5401020101 | D32: 间接费 | E32: 3 | N32: =X32 -> 0 | P32: =N32+O32 -> 0 | T32: =R32+S32 -> 0 | U32: =N32/P32 -> #DIV/0! | V32: =X32 -> 0 | X32: =SUM(SUMIF(项目收支汇总表!A5:A306,{"4.2.1.1","4.2.1.2","4.2.1.3","4.2.1.5","4.2.1.6"},项目收支汇总表!C5:C306)) -> 0 | Y32: =X32/N32 -> #DIV/0! | Z32: =V32-X32 -> 0 | AB32: =N32-X32 -> 0 | AC32: =O32 -> 0 | AD32: =AB32+AC32 -> 0 | AH32: =(X32+AG32)/N32 -> #DIV/0! | AJ32: =(X32+AI32)/N32 -> #DIV/0!
A33: 2.1.1 | B33: 工资及福利费（派遣） | C33: 5401020102 | D33: 间接费 | E33: 3 | N33: =X33 -> 0 | P33: =N33+O33 -> 0 | T33: =R33+S33 -> 0 | U33: =N33/P33 -> #DIV/0! | V33: =X33 -> 0 | X33: =LOOKUP(1,0/(项目收支汇总表!A5:A306="4.2.1.4"),项目收支汇总表!C5:C306) -> 0 | Y33: =X33/N33 -> #DIV/0! | Z33: =V33-X33 -> 0 | AB33: =N33-X33 -> 0 | AC33: =O33 -> 0 | AD33: =AB33+AC33 -> 0 | AH33: =(X33+AG33)/N33 -> #DIV/0! | AJ33: =(X33+AI33)/N33 -> #DIV/0!
A34: 2.2 | B34: 其他间接费 | C34: 54010202 | D34: 间接费 | E34: 2 | N34: =SUM(N35:N52) -> 0 | O34: =SUM(O35:O52) -> 0 | P34: =N34+O34 -> 0 | Q34: =SUM(Q35:Q52) -> 0 | R34: =SUM(R35:R52) -> 0 | S34: =SUM(S35:S52) -> 0 | T34: =R34+S34 -> 0 | U34: =N34/P34 -> #DIV/0! | V34: =SUM(V35:V52) -> 0 | W34: =SUM(W35:W52) -> 0 | X34: =SUM(X35:X52) -> 0 | Y34: =X34/N34 -> #DIV/0! | Z34: =V34-X34 -> 0 | AA34: =SUM(AA35:AA52) -> 0 | AB34: =N34-X34 -> 0 | AC34: =O34 -> 0 | AD34: =AB34+AC34 -> 0 | AG34: =SUM(AG35:AG52) -> 0 | AH34: =(X34+AG34)/N34 -> #DIV/0! | AI34: =SUM(AI35:AI52) -> 0 | AJ34: =(X34+AI34)/N34 -> #DIV/0! | AK34: =SUM(AK35:AK52) -> 0 | AL34: =SUM(AL35:AL52) -> 0
A35: 2.2.1 | B35: 职工教育经费 | C35: 5401020201 | D35: 间接费 | E35: 3 | N35: =X35 -> 0 | P35: =N35+O35 -> 0 | T35: =R35+S35 -> 0 | U35: =N35/P35 -> #DIV/0! | V35: =X35 -> 0 | X35: =LOOKUP(1,0/(项目收支汇总表!A5:A306="4.2.1.7"),项目收支汇总表!C5:C306) -> 0 | Y35: =X35/N35 -> #DIV/0! | Z35: =V35-X35 -> 0 | AB35: =N35-X35 -> 0 | AC35: =O35 -> 0 | AD35: =AB35+AC35 -> 0 | AH35: =(X35+AG35)/N35 -> #DIV/0! | AJ35: =(X35+AI35)/N35 -> #DIV/0!
A36: 2.2.2 | B36: 工会经费 | C36: 5401020202 | D36: 间接费 | E36: 3 | N36: =X36 -> 0 | P36: =N36+O36 -> 0 | T36: =R36+S36 -> 0 | U36: =N36/P36 -> #DIV/0! | V36: =X36 -> 0 | X36: =LOOKUP(1,0/(项目收支汇总表!A5:A306="4.2.1.8"),项目收支汇总表!C5:C306) -> 0 | Y36: =X36/N36 -> #DIV/0! | Z36: =V36-X36 -> 0 | AB36: =N36-X36 -> 0 | AC36: =O36 -> 0 | AD36: =AB36+AC36 -> 0 | AH36: =(X36+AG36)/N36 -> #DIV/0! | AJ36: =(X36+AI36)/N36 -> #DIV/0!
A37: 2.2.3 | B37: 折旧及摊销 | C37: 5401020203 | D37: 间接费 | E37: 3 | N37: =X37 -> 0 | P37: =N37+O37 -> 0 | T37: =R37+S37 -> 0 | U37: =N37/P37 -> #DIV/0! | V37: =X37 -> 0 | X37: =LOOKUP(1,0/(项目收支汇总表!A5:A306="4.2.1.9"),项目收支汇总表!C5:C306) -> 0 | Y37: =X37/N37 -> #DIV/0! | Z37: =V37-X37 -> 0 | AB37: =N37-X37 -> 0 | AC37: =O37 -> 0 | AD37: =AB37+AC37 -> 0 | AH37: =(X37+AG37)/N37 -> #DIV/0! | AJ37: =(X37+AI37)/N37 -> #DIV/0!
A38: 2.2.4 | B38: 办公费 | C38: 5401020204 | D38: 间接费 | E38: 3 | N38: =X38 -> 0 | P38: =N38+O38 -> 0 | T38: =R38+S38 -> 0 | U38: =N38/P38 -> #DIV/0! | V38: =X38 -> 0 | X38: =LOOKUP(1,0/(项目收支汇总表!A5:A306="4.2.1.10"),项目收支汇总表!C5:C306) -> 0 | Y38: =X38/N38 -> #DIV/0! | Z38: =V38-X38 -> 0 | AB38: =N38-X38 -> 0 | AC38: =O38 -> 0 | AD38: =AB38+AC38 -> 0 | AH38: =(X38+AG38)/N38 -> #DIV/0! | AJ38: =(X38+AI38)/N38 -> #DIV/0!
A39: 2.2.5 | B39: 会议费 | C39: 5401020205 | D39: 间接费 | E39: 3 | N39: =X39 -> 0 | P39: =N39+O39 -> 0 | T39: =R39+S39 -> 0 | U39: =N39/P39 -> #DIV/0! | V39: =X39 -> 0 | X39: =LOOKUP(1,0/(项目收支汇总表!A5:A306="4.2.1.11"),项目收支汇总表!C5:C306) -> 0 | Y39: =X39/N39 -> #DIV/0! | Z39: =V39-X39 -> 0 | AB39: =N39-X39 -> 0 | AC39: =O39 -> 0 | AD39: =AB39+AC39 -> 0 | AH39: =(X39+AG39)/N39 -> #DIV/0! | AJ39: =(X39+AI39)/N39 -> #DIV/0!
A40: 2.2.6 | B40: 摊销费 | C40: 5401020206 | D40: 间接费 | E40: 3 | N40: =X40 -> 0 | P40: =N40+O40 -> 0 | T40: =R40+S40 -> 0 | U40: =N40/P40 -> #DIV/0! | V40: =X40 -> 0 | X40: =LOOKUP(1,0/(项目收支汇总表!A5:A306="4.2.1.12"),项目收支汇总表!C5:C306) -> 0 | Y40: =X40/N40 -> #DIV/0! | Z40: =V40-X40 -> 0 | AB40: =N40-X40 -> 0 | AC40: =O40 -> 0 | AD40: =AB40+AC40 -> 0 | AH40: =(X40+AG40)/N40 -> #DIV/0! | AJ40: =(X40+AI40)/N40 -> #DIV/0!
A41: 2.2.7 | B41: 汽车费用 | C41: 5401020207 | D41: 间接费 | E41: 3 | N41: =X41 -> 0 | P41: =N41+O41 -> 0 | T41: =R41+S41 -> 0 | U41: =N41/P41 -> #DIV/0! | V41: =X41 -> 0 | X41: =LOOKUP(1,0/(项目收支汇总表!A5:A306="4.2.1.13"),项目收支汇总表!C5:C306) -> 0 | Y41: =X41/N41 -> #DIV/0! | Z41: =V41-X41 -> 0 | AB41: =N41-X41 -> 0 | AC41: =O41 -> 0 | AD41: =AB41+AC41 -> 0 | AH41: =(X41+AG41)/N41 -> #DIV/0! | AJ41: =(X41+AI41)/N41 -> #DIV/0!
A42: 2.2.8 | B42: 出国费 | C42: 5401020208 | D42: 间接费 | E42: 3 | N42: =X42 -> 0 | P42: =N42+O42 -> 0 | T42: =R42+S42 -> 0 | U42: =N42/P42 -> #DIV/0! | V42: =X42 -> 0 | X42: =LOOKUP(1,0/(项目收支汇总表!A5:A306="4.2.1.15"),项目收支汇总表!C5:C306) -> 0 | Y42: =X42/N42 -> #DIV/0! | Z42: =V42-X42 -> 0 | AB42: =N42-X42 -> 0 | AC42: =O42 -> 0 | AD42: =AB42+AC42 -> 0 | AH42: =(X42+AG42)/N42 -> #DIV/0! | AJ42: =(X42+AI42)/N42 -> #DIV/0!
A43: 2.2.9 | B43: 交通费 | C43: 5401020209 | D43: 间接费 | E43: 3 | N43: =X43 -> 0 | P43: =N43+O43 -> 0 | T43: =R43+S43 -> 0 | U43: =N43/P43 -> #DIV/0! | V43: =X43 -> 0 | X43: =LOOKUP(1,0/(项目收支汇总表!A5:A306="4.2.1.16"),项目收支汇总表!C5:C306) -> 0 | Y43: =X43/N43 -> #DIV/0! | Z43: =V43-X43 -> 0 | AB43: =N43-X43 -> 0 | AC43: =O43 -> 0 | AD43: =AB43+AC43 -> 0 | AH43: =(X43+AG43)/N43 -> #DIV/0! | AJ43: =(X43+AI43)/N43 -> #DIV/0!
A44: 2.2.10 | B44: 差旅费 | C44: 5401020210 | D44: 间接费 | E44: 3 | N44: =X44 -> 0 | P44: =N44+O44 -> 0 | T44: =R44+S44 -> 0 | U44: =N44/P44 -> #DIV/0! | V44: =X44 -> 0 | X44: =LOOKUP(1,0/(项目收支汇总表!A5:A306="4.2.1.17"),项目收支汇总表!C5:C306) -> 0 | Y44: =X44/N44 -> #DIV/0! | Z44: =V44-X44 -> 0 | AB44: =N44-X44 -> 0 | AC44: =O44 -> 0 | AD44: =AB44+AC44 -> 0 | AH44: =(X44+AG44)/N44 -> #DIV/0! | AJ44: =(X44+AI44)/N44 -> #DIV/0!
A45: 2.2.11 | B45: 租赁费 | C45: 5401020211 | D45: 间接费 | E45: 3 | N45: =X45 -> 0 | P45: =N45+O45 -> 0 | T45: =R45+S45 -> 0 | U45: =N45/P45 -> #DIV/0! | V45: =X45 -> 0 | X45: =LOOKUP(1,0/(项目收支汇总表!A5:A306="4.2.1.18"),项目收支汇总表!C5:C306) -> 0 | Y45: =X45/N45 -> #DIV/0! | Z45: =V45-X45 -> 0 | AB45: =N45-X45 -> 0 | AC45: =O45 -> 0 | AD45: =AB45+AC45 -> 0 | AH45: =(X45+AG45)/N45 -> #DIV/0! | AJ45: =(X45+AI45)/N45 -> #DIV/0!
A46: 2.2.12 | B46: 供暖费 | C46: 5401020212 | D46: 间接费 | E46: 3 | N46: =X46 -> 0 | P46: =N46+O46 -> 0 | T46: =R46+S46 -> 0 | U46: =N46/P46 -> #DIV/0! | V46: =X46 -> 0 | X46: =LOOKUP(1,0/(项目收支汇总表!A5:A306="4.2.1.19"),项目收支汇总表!C5:C306) -> 0 | Y46: =X46/N46 -> #DIV/0! | Z46: =V46-X46 -> 0 | AB46: =N46-X46 -> 0 | AC46: =O46 -> 0 | AD46: =AB46+AC46 -> 0 | AH46: =(X46+AG46)/N46 -> #DIV/0! | AJ46: =(X46+AI46)/N46 -> #DIV/0!
A47: 2.2.13 | B47: 劳动保护费 | C47: 5401020213 | D47: 间接费 | E47: 3 | N47: =X47 -> 0 | P47: =N47+O47 -> 0 | T47: =R47+S47 -> 0 | U47: =N47/P47 -> #DIV/0! | V47: =X47 -> 0 | X47: =LOOKUP(1,0/(项目收支汇总表!A5:A306="4.2.1.20"),项目收支汇总表!C5:C306) -> 0 | Y47: =X47/N47 -> #DIV/0! | Z47: =V47-X47 -> 0 | AB47: =N47-X47 -> 0 | AC47: =O47 -> 0 | AD47: =AB47+AC47 -> 0 | AH47: =(X47+AG47)/N47 -> #DIV/0! | AJ47: =(X47+AI47)/N47 -> #DIV/0!
A48: 2.2.14 | B48: 保安清洁绿化费 | C48: 5401020214 | D48: 间接费 | E48: 3 | N48: =X48 -> 0 | P48: =N48+O48 -> 0 | T48: =R48+S48 -> 0 | U48: =N48/P48 -> #DIV/0! | V48: =X48 -> 0 | X48: =LOOKUP(1,0/(项目收支汇总表!A5:A306="4.2.1.21"),项目收支汇总表!C5:C306) -> 0 | Y48: =X48/N48 -> #DIV/0! | Z48: =V48-X48 -> 0 | AB48: =N48-X48 -> 0 | AC48: =O48 -> 0 | AD48: =AB48+AC48 -> 0 | AH48: =(X48+AG48)/N48 -> #DIV/0! | AJ48: =(X48+AI48)/N48 -> #DIV/0!
A49: 2.2.15 | B49: 专业服务费 | C49: 5401020215 | D49: 间接费 | E49: 3 | N49: =X49 -> 0 | P49: =N49+O49 -> 0 | T49: =R49+S49 -> 0 | U49: =N49/P49 -> #DIV/0! | V49: =X49 -> 0 | X49: =LOOKUP(1,0/(项目收支汇总表!A5:A306="4.2.1.22"),项目收支汇总表!C5:C306) -> 0 | Y49: =X49/N49 -> #DIV/0! | Z49: =V49-X49 -> 0 | AB49: =N49-X49 -> 0 | AC49: =O49 -> 0 | AD49: =AB49+AC49 -> 0 | AH49: =(X49+AG49)/N49 -> #DIV/0! | AJ49: =(X49+AI49)/N49 -> #DIV/0!
A50: 2.2.16 | B50: 其他间接费 | C50: 5401020299 | D50: 间接费 | E50: 3 | N50: =X50 -> 0 | P50: =N50+O50 -> 0 | T50: =R50+S50 -> 0 | U50: =N50/P50 -> #DIV/0! | V50: =X50 -> 0 | X50: =SUM(SUMIF(项目收支汇总表!A5:A306,{"4.2.1.23","4.3.1","4.3.3","4.3.4","4.3.5","4.3.13","4.3.15"},项目收支汇总表!C5:C306))+LOOKUP(1,0/(项目收支汇总表!A5:A306="3.3"),项目收支汇总表!C5:C306)-LOOKUP(1,0/(项目收支汇总表!A5:A306="3.3.1"),项目收支汇总表!C5:C306) -> 0 | Y50: =X50/N50 -> #DIV/0! | Z50: =V50-X50 -> 0 | AB50: =N50-X50 -> 0 | AC50: =O50 -> 0 | AD50: =AB50+AC50 -> 0 | AH50: =(X50+AG50)/N50 -> #DIV/0! | AJ50: =(X50+AI50)/N50 -> #DIV/0!
A51: 2.2.17 | B51: 固定资产 | C51: 5401020216 | D51: 间接费 | E51: 3 | N51: =X51 -> 0 | P51: =N51+O51 -> 0 | T51: =R51+S51 -> 0 | U51: =N51/P51 -> #DIV/0! | V51: =X51 -> 0 | X51: =LOOKUP(1,0/(项目收支汇总表!A5:A306="4.3.2"),项目收支汇总表!C5:C306) -> 0 | Y51: =X51/N51 -> #DIV/0! | Z51: =V51-X51 -> 0 | AB51: =N51-X51 -> 0 | AC51: =O51 -> 0 | AD51: =AB51+AC51 -> 0 | AH51: =(X51+AG51)/N51 -> #DIV/0! | AJ51: =(X51+AI51)/N51 -> #DIV/0!
A52: 2.2.18 | B52: 无证施工罚款、协调费 | C52: 5401020217 | D52: 间接费 | E52: 3 | N52: =X52 -> 0 | P52: =N52+O52 -> 0 | T52: =R52+S52 -> 0 | U52: =N52/P52 -> #DIV/0! | V52: =X52 -> 0 | Y52: =X52/N52 -> #DIV/0! | Z52: =V52-X52 -> 0 | AB52: =N52-X52 -> 0 | AC52: =O52 -> 0 | AD52: =AB52+AC52 -> 0 | AH52: =(X52+AG52)/N52 -> #DIV/0! | AJ52: =(X52+AI52)/N52 -> #DIV/0!
A53: 2.3 | B53: 业务招待费 | C53: 54010203 | D53: 间接费 | E53: 2 | N53: =X53 -> 0 | P53: =N53+O53 -> 0 | T53: =R53+S53 -> 0 | U53: =N53/P53 -> #DIV/0! | V53: =X53 -> 0 | X53: =LOOKUP(1,0/(项目收支汇总表!A5:A306="4.2.1.14"),项目收支汇总表!C5:C306) -> 0 | Y53: =X53/N53 -> #DIV/0! | Z53: =V53-X53 -> 0 | AB53: =N53-X53 -> 0 | AC53: =O53 -> 0 | AD53: =AB53+AC53 -> 0 | AH53: =(X53+AG53)/N53 -> #DIV/0! | AJ53: =(X53+AI53)/N53 -> #DIV/0!
A54: 2.4 | B54: 点交费 | C54: 54010204 | D54: 间接费 | E54: 2 | N54: =X54 -> 0 | P54: =N54+O54 -> 0 | T54: =R54+S54 -> 0 | U54: =N54/P54 -> #DIV/0! | V54: =X54 -> 0 | Y54: =X54/N54 -> #DIV/0! | Z54: =V54-X54 -> 0 | AB54: =N54-X54 -> 0 | AC54: =O54 -> 0 | AD54: =AB54+AC54 -> 0 | AH54: =(X54+AG54)/N54 -> #DIV/0! | AJ54: =(X54+AI54)/N54 -> #DIV/0!
A55: 2.5 | B55: 事业部费用分摊 | C55: 54010205 | D55: 间接费 | E55: 2 | N55: =X55 -> 0 | P55: =N55+O55 -> 0 | T55: =R55+S55 -> 0 | U55: =N55/P55 -> #DIV/0! | V55: =X55 -> 0 | Y55: =X55/N55 -> #DIV/0! | Z55: =V55-X55 -> 0 | AB55: =N55-X55 -> 0 | AC55: =O55 -> 0 | AD55: =AB55+AC55 -> 0 | AH55: =(X55+AG55)/N55 -> #DIV/0! | AJ55: =(X55+AI55)/N55 -> #DIV/0!
A56: 2.6 | B56: 奖金 | C56: 54010206 | D56: 间接费 | E56: 2 | N56: =X56 -> 0 | P56: =N56+O56 -> 0 | T56: =R56+S56 -> 0 | U56: =N56/P56 -> #DIV/0! | V56: =X56 -> 0 | Y56: =X56/N56 -> #DIV/0! | Z56: =V56-X56 -> 0 | AB56: =N56-X56 -> 0 | AC56: =O56 -> 0 | AD56: =AB56+AC56 -> 0 | AH56: =(X56+AG56)/N56 -> #DIV/0! | AJ56: =(X56+AI56)/N56 -> #DIV/0!
A57: 三 | B57: 财务成本 | C57: 540103 | D57: 财务费用 | E57: 1 | N57: =N58+N59+N60 -> 0 | O57: =O58+O59+O60 -> 0 | P57: =N57+O57 -> 0 | Q57: =Q58+Q59+Q60 -> 0 | R57: =R58+R59+R60 -> 0 | S57: =S58+S59+S60 -> 0 | T57: =R57+S57 -> 0 | U57: =N57/P57 -> #DIV/0! | V57: =V58+V59+V60 -> 0 | W57: =W58+W59+W60 -> 0 | X57: =X58+X59+X60 -> 0 | Y57: =X57/N57 -> #DIV/0! | Z57: =V57-X57 -> 0 | AA57: =AA58+AA59+AA60 -> 0 | AB57: =N57-X57 -> 0 | AC57: =O57 -> 0 | AD57: =AB57+AC57 -> 0 | AG57: =AG58+AG59+AG60 -> 0 | AH57: =(X57+AG57)/N57 -> #DIV/0! | AI57: =AI58+AI59+AI60 -> 0 | AJ57: =(X57+AI57)/N57 -> #DIV/0! | AK57: =AK58+AK59+AK60 -> 0 | AL57: =AL58+AL59+AL60 -> 0
A58: 3.1 | B58: 贴现息 | C58: 54010301 | D58: 财务费用 | E58: 2 | N58: =X58 -> 0 | P58: =N58+O58 -> 0 | T58: =R58+S58 -> 0 | U58: =N58/P58 -> #DIV/0! | V58: =X58 -> 0 | X58: =LOOKUP(1,0/(项目收支汇总表!A5:A306="4.2.2.4"),项目收支汇总表!C5:C306) -> 0 | Y58: =X58/N58 -> #DIV/0! | Z58: =V58-X58 -> 0 | AB58: =N58-X58 -> 0 | AC58: =O58 -> 0 | AD58: =AB58+AC58 -> 0 | AH58: =(X58+AG58)/N58 -> #DIV/0! | AJ58: =(X58+AI58)/N58 -> #DIV/0!
A59: 3.2 | B59: 利息 | C59: 54010302 | D59: 财务费用 | E59: 2 | N59: =X59 -> 0 | P59: =N59+O59 -> 0 | T59: =R59+S59 -> 0 | U59: =N59/P59 -> #DIV/0! | V59: =X59 -> 0 | X59: =LOOKUP(1,0/(项目收支汇总表!A5:A306="3.3.1"),项目收支汇总表!C5:C306) -> 0 | Y59: =X59/N59 -> #DIV/0! | Z59: =V59-X59 -> 0 | AB59: =N59-X59 -> 0 | AC59: =O59 -> 0 | AD59: =AB59+AC59 -> 0 | AH59: =(X59+AG59)/N59 -> #DIV/0! | AJ59: =(X59+AI59)/N59 -> #DIV/0!
A60: 3.3 | B60: 工程抵房预亏（赚） | C60: 54010303 | D60: 财务费用 | E60: 2 | N60: =X60 -> 0 | P60: =N60+O60 -> 0 | T60: =R60+S60 -> 0 | U60: =N60/P60 -> #DIV/0! | V60: =X60 -> 0 | Y60: =X60/N60 -> #DIV/0! | Z60: =V60-X60 -> 0 | AB60: =N60-X60 -> 0 | AC60: =O60 -> 0 | AD60: =AB60+AC60 -> 0 | AH60: =(X60+AG60)/N60 -> #DIV/0! | AJ60: =(X60+AI60)/N60 -> #DIV/0!
A61: 四 | B61: 税金 | C61: 540104 | D61: 税金 | E61: 1 | N61: =N62+N63+N64+N65 -> 0 | O61: =O62+O63+O64+O65 -> 0 | P61: =N61+O61 -> 0 | Q61: =Q62+Q63+Q64+Q65 -> 0 | R61: =R62+R63+R64+R65 -> 0 | S61: =S62+S63+S64+S65 -> 0 | T61: =R61+S61 -> 0 | U61: =N61/P61 -> #DIV/0! | V61: =V62+V63+V64+V65 -> 0 | W61: =W62+W63+W64+W65 -> 0 | X61: =X62+X63+X64+X65 -> 0 | Y61: =X61/N61 -> #DIV/0! | Z61: =V61-X61 -> 0 | AA61: =AA62+AA63+AA64+AA65 -> 0 | AB61: =N61-X61 -> 0 | AC61: =O61 -> 0 | AD61: =AB61+AC61 -> 0 | AG61: =AG62+AG63+AG64+AG65 -> 0 | AH61: =(X61+AG61)/N61 -> #DIV/0! | AI61: =AI62+AI63+AI64+AI65 -> 0 | AJ61: =(X61+AI61)/N61 -> #DIV/0! | AK61: =AK62+AK63+AK64+AK65 -> 0 | AL61: =AL62+AL63+AL64+AL65 -> 0
A62: 4.1 | B62: 增值税 | C62: 54010401 | D62: 税费 | E62: 2 | N62: =X62 -> 0 | O62: =('项目月度业主产值表-表3.1'!O6*项目收支汇总表!C115)-N62 -> 0 | P62: =N62+O62 -> 0 | T62: =R62+S62 -> 0 | U62: =N62/P62 -> #DIV/0! | V62: =X62 -> 0 | X62: =LOOKUP(1,0/(项目收支汇总表!A5:A306="4.3.6"),项目收支汇总表!C5:C306) -> 0 | Y62: =X62/N62 -> #DIV/0! | Z62: =V62-X62 -> 0 | AB62: =N62-X62 -> 0 | AC62: =O62 -> 0 | AD62: =AB62+AC62 -> 0 | AH62: =(X62+AG62)/N62 -> #DIV/0! | AJ62: =(X62+AI62)/N62 -> #DIV/0!
A63: 4.2 | B63: 附加税 | C63: 54010402 | D63: 税费 | E63: 2 | N63: =X63 -> 0 | O63: =O62*0.12 -> 0 | P63: =N63+O63 -> 0 | T63: =R63+S63 -> 0 | U63: =N63/P63 -> #DIV/0! | V63: =X63 -> 0 | X63: =LOOKUP(1,0/(项目收支汇总表!A5:A306="4.3.7"),项目收支汇总表!C5:C306) -> 0 | Y63: =X63/N63 -> #DIV/0! | Z63: =V63-X63 -> 0 | AB63: =N63-X63 -> 0 | AC63: =O63 -> 0 | AD63: =AB63+AC63 -> 0 | AH63: =(X63+AG63)/N63 -> #DIV/0! | AJ63: =(X63+AI63)/N63 -> #DIV/0!
A64: 4.3 | B64: 印花税 | C64: 54010403 | D64: 税费 | E64: 2 | N64: =X64 -> 0 | P64: =N64+O64 -> 0 | T64: =R64+S64 -> 0 | U64: =N64/P64 -> #DIV/0! | V64: =X64 -> 0 | X64: =LOOKUP(1,0/(项目收支汇总表!A5:A306="4.3.8"),项目收支汇总表!C5:C306) -> 0 | Y64: =X64/N64 -> #DIV/0! | Z64: =V64-X64 -> 0 | AB64: =N64-X64 -> 0 | AC64: =O64 -> 0 | AD64: =AB64+AC64 -> 0 | AH64: =(X64+AG64)/N64 -> #DIV/0! | AJ64: =(X64+AI64)/N64 -> #DIV/0! | AP64: 万分之三
A65: 4.4 | B65: 其他税费 | C65: 54010499 | D65: 税费 | E65: 2 | N65: =X65 -> 0 | P65: =N65+O65 -> 0 | T65: =R65+S65 -> 0 | U65: =N65/P65 -> #DIV/0! | V65: =X65 -> 0 | X65: =SUM(SUMIF(项目收支汇总表!A5:A306,{"4.3.9","4.3.10"},项目收支汇总表!C5:C306)) -> 0 | Y65: =X65/N65 -> #DIV/0! | Z65: =V65-X65 -> 0 | AB65: =N65-X65 -> 0 | AC65: =O65 -> 0 | AD65: =AB65+AC65 -> 0 | AH65: =(X65+AG65)/N65 -> #DIV/0! | AJ65: =(X65+AI65)/N65 -> #DIV/0! | AP65: 包括但不限于环境保护税
A66: 五 | B66: 公司管理费（ %） | C66: 540105 | D66: 公司管理费 | E66: 1 | N66: =X66 -> 0 | O66: =($P$2*'项目月度业主产值表-表3.1'!O6)-N66 -> 0 | P66: =N66+O66 -> 0 | T66: =R66+S66 -> 0 | U66: =N66/P66 -> #DIV/0! | V66: =X66 -> 0 | X66: =LOOKUP(1,0/(项目收支汇总表!A5:A306="3.2"),项目收支汇总表!C5:C306) -> 0 | Y66: =X66/N66 -> #DIV/0! | Z66: =V66-X66 -> 0 | AB66: =N66-X66 -> 0 | AC66: =O66 -> 0 | AD66: =AB66+AC66 -> 0 | AH66: =(X66+AG66)/N66 -> #DIV/0! | AJ66: =(X66+AI66)/N66 -> #DIV/0!
A67: 六 | B67: 不可预见费（ %） | C67: 540106 | D67: 一般风险费 | E67: 1 | N67: =X67 -> 0 | P67: =N67+O67 -> 0 | T67: =R67+S67 -> 0 | U67: =N67/P67 -> #DIV/0! | V67: =X67 -> 0 | Y67: =X67/N67 -> #DIV/0! | Z67: =V67-X67 -> 0 | AB67: =N67-X67 -> 0 | AC67: =O67 -> 0 | AD67: =AB67+AC67 -> 0 | AH67: =(X67+AG67)/N67 -> #DIV/0! | AJ67: =(X67+AI67)/N67 -> #DIV/0!
A68: 七 | B68: 暂列（暂估）金额 | C68: 540107 | D68: 暂列（暂估）金额 | E68: 1 | N68: =X68 -> 0 | P68: =N68+O68 -> 0 | T68: =R68+S68 -> 0 | U68: =N68/P68 -> #DIV/0! | V68: =X68 -> 0 | Y68: =X68/N68 -> #DIV/0! | Z68: =V68-X68 -> 0 | AB68: =N68-X68 -> 0 | AC68: =O68 -> 0 | AD68: =AB68+AC68 -> 0 | AH68: =(X68+AG68)/N68 -> #DIV/0! | AJ68: =(X68+AI68)/N68 -> #DIV/0!
A69: 八 | B69: 成本汇总 | C69: 540108 | D69: 总成本 | E69: 1 | N69: =N7+N30+N57+N61+N66+N67+N68 -> 0 | O69: =O7+O30+O57+O61+O66+O67+O68 -> 0 | P69: =N69+O69 -> 0 | Q69: =Q7+Q30+Q57+Q61+Q66+Q67+Q68 -> 0 | R69: =R7+R30+R57+R61+R66+R67+R68 -> 0 | S69: =S7+S30+S57+S61+S66+S67+S68 -> 0 | T69: =R69+S69 -> 0 | U69: =N69/P69 -> #DIV/0! | V69: =V7+V30+V57+V61+V66+V67+V68 -> 0 | W69: =W7+W30+W57+W61+W66+W67+W68 -> 0 | X69: =X7+X30+X57+X61+X66+X67+X68 -> 0 | Y69: =X69/N69 -> #DIV/0! | Z69: =V69-X69 -> 0 | AA69: =AA7+AA30+AA57+AA61+AA66+AA67+AA68 -> 0 | AB69: =N69-X69 -> 0 | AC69: =O69 -> 0 | AD69: =AB69+AC69 -> 0 | AG69: =AG7+AG30+AG57+AG61+AG66+AG67+AG68 -> 0 | AH69: =(X69+AG69)/N69 -> #DIV/0! | AI69: =AI7+AI30+AI57+AI61+AI66+AI67+AI68 -> 0 | AJ69: =(X69+AI69)/N69 -> #DIV/0! | AK69: =AK7+AK30+AK57+AK61+AK66+AK67+AK68 -> 0 | AL69: =AL7+AL30+AL57+AL61+AL66+AL67+AL68 -> 0
A70: 九 | B70: 往来资金支出（不计入成本） | C70: 540120 | E70: 1 | V70: =V71+V76+V80 -> 0 | W70: =W71+W76+W80 -> 0 | X70: =X71+X76+X80 -> 0 | Z70: 0 | AA70: =AA71+AA76+AA80 -> 0 | AG70: =AG71+AG76+AG80 -> 0 | AI70: =AI71+AI76+AI80 -> 0 | AK70: =AK71+AK76+AK80 -> 0 | AL70: =AL71+AL76+AL80 -> 0
A71: 9.1 | B71: 借款本金返还 | C71: 54012001 | E71: 2 | V71: =SUM(V72:V75) -> 0 | W71: =SUM(W72:W75) -> 0 | X71: =SUM(X72:X75) -> 0 | Z71: 0 | AA71: =SUM(AA72:AA75) -> 0 | AG71: =SUM(AG72:AG75) -> 0 | AI71: =SUM(AI72:AI75) -> 0 | AK71: =SUM(AK72:AK75) -> 0 | AL71: =SUM(AL72:AL75) -> 0
A72: 9.1.1 | B72: 内部项目资金拆借本金返还支出 | C72: 5401200101 | E72: 3 | X72: =LOOKUP(1,0/(项目收支汇总表!A5:A306="2.9.2"),项目收支汇总表!C5:C306)+LOOKUP(1,0/(项目收支汇总表!A5:A306="2.9.3"),项目收支汇总表!C5:C306) -> 0 | Z72: 0
A73: 9.1.2 | B73: 公司借款本金返还支出 | C73: 5401200102 | E73: 3 | X73: =LOOKUP(1,0/(项目收支汇总表!A5:A306="2.10.2"),项目收支汇总表!C5:C306)+LOOKUP(1,0/(项目收支汇总表!A5:A306="2.10.3"),项目收支汇总表!C5:C306) -> 0 | Z73: 0
A74: 9.1.3 | B74: 公司借票据返还（兑付） | C74: 5401200103 | E74: 3 | X74: 0 | Z74: 0
A75: 9.1.4 | B75: 自筹往来款返还支出 | C75: 5401200104 | E75: 3 | X75: =LOOKUP(1,0/(项目收支汇总表!A5:A306="2.11.2"),项目收支汇总表!C5:C306) -> 0 | Z75: 0
A76: 9.2 | B76: 保证金支出 | C76: 54012002 | E76: 2 | V76: =SUM(V77:V79) -> 0 | W76: =SUM(W77:W79) -> 0 | X76: =SUM(X77:X79) -> 0 | Z76: 0 | AA76: =SUM(AA77:AA79) -> 0 | AG76: =SUM(AG77:AG79) -> 0 | AI76: =SUM(AI77:AI79) -> 0 | AK76: =SUM(AK77:AK79) -> 0 | AL76: =SUM(AL77:AL79) -> 0
A77: 9.2.1 | B77: 分供方保证金返还支出 | C77: 5401200201 | E77: 3 | X77: =LOOKUP(1,0/(项目收支汇总表!A5:A306="2.12.2"),项目收支汇总表!C5:C306) -> 0 | Z77: 0
A78: 9.2.2 | B78: 业主保证金支出 | C78: 5401200202 | E78: 3 | X78: =LOOKUP(1,0/(项目收支汇总表!A5:A306="2.12.4"),项目收支汇总表!C5:C306) -> 0 | Z78: 0
A79: 9.2.3 | B79: 其他保证金支出 | C79: 5401200299 | E79: 3 | X79: =LOOKUP(1,0/(项目收支汇总表!A5:A306="2.13.2"),项目收支汇总表!C5:C306) -> 0 | Z79: 0
A80: 9.3 | B80: 项目往来借支款 | C80: 54012003 | E80: 2 | X80: =LOOKUP(1,0/(项目收支汇总表!A5:A306="4.3.11"),项目收支汇总表!C5:C306)+LOOKUP(1,0/(项目收支汇总表!A5:A306="4.3.12"),项目收支汇总表!C5:C306) -> 0
A81: 十 | B81: 资金合计（八+九） | C81: 540190 | E81: 1 | N81: =N69+N70 -> 0 | O81: =O69+O70 -> 0 | P81: =N81+O81 -> 0 | Q81: =Q69+Q70 -> 0 | R81: =R69+R70 -> 0 | S81: =S69+S70 -> 0 | T81: =R81+S81 -> 0 | U81: =N81/P81 -> #DIV/0! | V81: =V69+V70 -> 0 | W81: =W69+W70 -> 0 | X81: =X69+X70 -> 0 | Y81: =X81/N81 -> #DIV/0! | Z81: =Z69+Z70 -> 0 | AA81: =AA69+AA70 -> 0 | AB81: =AB69+AB70 -> 0 | AG81: =AG69+AG70 -> 0 | AH81: =(X81+AG81)/N81 -> #DIV/0! | AI81: =AI69+AI70 -> 0 | AJ81: =AJ69+AJ70 -> #DIV/0! | AK81: =AK69+AK70 -> 0 | AL81: =AL69+AL70 -> 0

Sheet 项目月度待确成本分析表-表3.2.1
A1: 表3.2.1 - 项目月度待确成本分析表
A2: 项目名称: | I2: 报告期间: | L2: 单位: 元
A3: 序号 | B3: 合同编码 | C3: 合同名称 | D3: 合同内容 | E3: 分/供商名称 | F3: 合同总金额 | G3: 付款比例 | H3: 税率 （%） | I3: 是否办理结算 | J3: 待确金额(含税) | K3: 主要原因分析 | L3: 备 注
A196: 说明：单项预估金额超过50万元，需提供详细计算式。 预估金额是指统计时点开累未确认成本。

Sheet 项目收支汇总表
A1: 项目收支汇总表
A2: 项目名称: | D2: 报告期间:
A3: 代码 | B3: 科目 | C3: 项目金额 | D3: 公司金额 | E3: 合计
A5: 1 | B5: 资金余额 | C5: =SUM(C6:C8) -> 0
A6: 1.1 | B6: 项目可用资金余额 | C6: 0
A7: 1.2 | B7: 承包人可用资金余额 | C7: 0
A8: 1.3 | B8: 项目不含资金拆借余额 | C8: 0
A9: 2 | B9: 收款金额 | C9: =SUM(C10:C21,C26,C31,C34,C39,C42,C43) -> 0
A10: 2.1 | B10: 工程款（业主计量收入） | C10: 0
A11: 2.1.1 | B11: 其中: 抵房 | C11: 0
A12: 2.1.2 | B12: 其中: 票据 | C12: 0
A13: 2.1.3 | B13: 其中: 专户收入 | C13: 0
A14: 2.2 | B14: 工程款（甲方代扣代缴） | C14: 0
A15: 2.3 | B15: 工程款（回款差额） | C15: 0
A16: 2.4 | B16: 工程款（甲指分包） | C16: 0
A17: 2.5 | B17: 工程款（甲供材） | C17: 0
A18: 2.6 | B18: 工程款（奖罚款） | C18: 0
A19: 2.7 | B19: 总包管理费 | C19: 0
A20: 2.8 | B20: 其他业主收入 | C20: 0
A21: 2.9 | B21: 关联方项目借支 | C21: =SUM(C22:C25) -> 0
A22: 2.9.1 | B22: 向其他项目借款流入 | C22: 0
A23: 2.9.2 | B23: 归还其他项目借款流出 | C23: 0
A24: 2.9.3 | B24: 其他项目借款流出 | C24: 0
A25: 2.9.4 | B25: 其他项目借款返还流入 | C25: 0
A26: 2.10 | B26: 公司借支余额 | C26: =SUM(C27:C30) -> 0
A27: 2.10.1 | B27: 向公司借款流入 | C27: 0
A28: 2.10.2 | B28: 归还公司借款流出 | C28: 0
A29: 2.10.3 | B29: 借款给公司流出 | C29: 0
A30: 2.10.4 | B30: 公司归还借款流入 | C30: 0
A31: 2.11 | B31: 自筹往来余额 | C31: =SUM(C32:C33) -> 0
A32: 2.11.1 | B32: 自筹往来款流入 | C32: 0
A33: 2.11.2 | B33: 自筹往来款流出 | C33: 0
A34: 2.12 | B34: 保证金 | C34: =SUM(C35:C38) -> 0
A35: 2.12.1 | B35: 分供方保证金流入 | C35: 0
A36: 2.12.2 | B36: 分供方保证金流出 | C36: 0
A37: 2.12.3 | B37: 业主保证金返还流入 | C37: 0
A38: 2.12.4 | B38: 业主保证金返还流出 | C38: 0
A39: 2.13 | B39: 其他保证金 | C39: =SUM(C40:C41) -> 0
A40: 2.13.1 | B40: 其他保证金流入 | C40: 0
A41: 2.13.2 | B41: 其他保证金流出 | C41: 0
A42: 2.14 | B42: 其他收入 | C42: 0
A43: 2.15 | B43: 利息收入 | C43: 0
A44: 3 | B44: 扣款金额 | C44: =SUM(C45:C47) -> 0
A45: 3.1 | B45: 归属公司部分产值收款 | C45: 0
A46: 3.2 | B46: 上交管理费 | C46: 0
A47: 3.3 | B47: 项目其他扣款 | C47: =SUM(C48) -> 0
A48: 3.3.1 | B48: 其中：资金占用利息 | C48: 0
A49: 4 | B49: 支出总计 | C49: =SUM(C50,C54,C97) -> 0 | D49: =SUM(D50,D54,D97) -> 0 | E49: =C49+D49 -> 0
A50: 4.1 | B50: 成本支出 | C50: =SUM(C51:C53) -> 0 | D50: =SUM(D51:D53) -> 0 | E50: =C50+D50 -> 0
A51: 4.1.1 | B51: 人工材料租赁已付款 | C51: 0 | D51: 0 | E51: =C51+D51 -> 0
A52: 4.1.2 | B52: 零星采购（未过应付） | C52: 0 | D52: 0 | E52: =C52+D52 -> 0
A53: 4.1.3 | B53: 未转回民工工资 | C53: 0 | D53: 0 | E53: =C53+D53 -> 0
A54: 4.2 | B54: 费用支出 | C54: =SUM(C55,C79) -> 0 | D54: =SUM(D55,D79) -> 0 | E54: =C54+D54 -> 0
A55: 4.2.1 | B55: 间接费用 | C55: 0 | D55: =SUM(D56:D78) -> 0 | E55: =C55+D55 -> 0
A56: 4.2.1.1 | B56: 工资 | C56: 0 | D56: 0 | E56: =C56+D56 -> 0
A57: 4.2.1.2 | B57: 绩效 | C57: 0 | D57: 0 | E57: =C57+D57 -> 0
A58: 4.2.1.3 | B58: 社保费 | C58: 0 | D58: 0 | E58: =C58+D58 -> 0
A59: 4.2.1.4 | B59: 劳务费 | C59: 0 | D59: 0 | E59: =C59+D59 -> 0
A60: 4.2.1.5 | B60: 住房公积金 | C60: 0 | D60: 0 | E60: =C60+D60 -> 0
A61: 4.2.1.6 | B61: 职工福利费 | C61: 0 | D61: 0 | E61: =C61+D61 -> 0
A62: 4.2.1.7 | B62: 职工教育经费 | C62: 0 | D62: 0 | E62: =C62+D62 -> 0
A63: 4.2.1.8 | B63: 工会经费 | C63: 0 | D63: 0 | E63: =C63+D63 -> 0
A64: 4.2.1.9 | B64: 折旧及摊销 | C64: 0 | D64: 0 | E64: =C64+D64 -> 0
A65: 4.2.1.10 | B65: 办公费 | C65: 0 | D65: 0 | E65: =C65+D65 -> 0
A66: 4.2.1.11 | B66: 会议费 | C66: 0 | D66: 0 | E66: =C66+D66 -> 0
A67: 4.2.1.12 | B67: 摊销费 | C67: 0 | D67: 0 | E67: =C67+D67 -> 0
... A78: 4.2.1.23 | B78: 其他间接费 | C78: 0 | D78: 0 | E78: =C78+D78 -> 0
A79: 4.2.2 | B79: 直接费用 | C79: =SUM(C80:C96) -> 0 | D79: =SUM(D80:D96) -> 0 | E79: =C79+D79 -> 0
A80: 4.2.2.1 | B80: 设计费 | C80: 0 | D80: 0 | E80: =C80+D80 -> 0
A81: 4.2.2.2 | B81: 运输费 | C81: 0 | D81: 0 | E81: =C81+D81 -> 0
A82: 4.2.2.3 | B82: 检测费 | C82: 0 | D82: 0 | E82: =C82+D82 -> 0
A83: 4.2.2.4 | B83: 贴现利息 | C83: 0 | D83: 0 | E83: =C83+D83 -> 0
A84: 4.2.2.5 | B84: 水费 | C84: 0 | D84: 0 | E84: =C84+D84 -> 0
A85: 4.2.2.6 | B85: 电费 | C85: 0 | D85: 0 | E85: =C85+D85 -> 0
A86: 4.2.2.7 | B86: 油费（机械用油） | C86: 0 | D86: 0 | E86: =C86+D86 -> 0
A87: 4.2.2.8 | B87: 修理费 | C87: 0 | D87: 0 | E87: =C87+D87 -> 0
A88: 4.2.2.9 | B88: 场地清理费 | C88: 0 | D88: 0 | E88: =C88+D88 -> 0
A89: 4.2.2.10 | B89: 排污费 | C89: 0 | D89: 0 | E89: =C89+D89 -> 0
A90: 4.2.2.11 | B90: 综合保险费 | C90: 0 | D90: 0 | E90: =C90+D90 -> 0
A91: 4.2.2.12 | B91: 保函手续费 | C91: 0 | D91: 0 | E91: =C91+D91 -> 0
... A96: 4.2.2.17 | B96: 其他直接费 | C96: 0 | D96: 0 | E96: =C96+D96 -> 0
A97: 4.3 | B97: 其他支出 | C97: =SUM(C98:C111) -> 0 | D97: =SUM(D98:D111) -> 0 | E97: =C97+D97 -> 0
A98: 4.3.1 | B98: 个人借支 | C98: 0 | D98: 0 | E98: =C98+D98 -> 0
A99: 4.3.2 | B99: 固定资产 | C99: 0 | D99: 0 | E99: =C99+D99 -> 0
A100: 4.3.3 | B100: 费用进项税 | C100: 0 | D100: 0 | E100: =C100+D100 -> 0
A101: 4.3.4 | B101: 待票报销支出 | C101: 0 | D101: 0 | E101: =C101+D101 -> 0
A102: 4.3.5 | B102: 预提费用 | C102: 0 | D102: 0 | E102: =C102+D102 -> 0
A103: 4.3.6 | B103: 增值税支出 | C103: 0 | D103: 0 | E103: =C103+D103 -> 0
A104: 4.3.7 | B104: 附加税费支出 | C104: 0 | D104: 0 | E104: =C104+D104 -> 0
A105: 4.3.8 | B105: 印花税 | C105: 0 | D105: 0 | E105: =C105+D105 -> 0
A106: 4.3.9 | B106: 其他税费支出 | C106: 0 | D106: 0 | E106: =C106+D106 -> 0
A107: 4.3.10 | B107: 企业所得税（预缴） | C107: 0 | D107: 0 | E107: =C107+D107 -> 0
A108: 4.3.11 | B108: 保证金 | C108: 0 | D108: 0 | E108: =C108+D108 -> 0
A109: 4.3.12 | B109: 押金 | C109: 0 | D109: 0 | E109: =C109+D109 -> 0
... A111: 4.3.15 | B111: 其他支出 | C111: 0 | D111: 0 | E111: =C111+D111 -> 0
A112: 5 | B112: 其他 | C112: 0
A113: 5.1 | B113: 管理费费率 | C113: 0.03
A114: 5.2 | B114: 开累已开发票 | C114: 0
A115: 5.3 | B115: 增值税税负率 | C115: 0.05
